Workbook
Name \0: #REF!
Name \1: #REF!
Name \a: #N/A
Name \b: #N/A
Name \C: #REF!
Name \l: #REF!
Name \m: #REF!
Name \n: #REF!
Name \p: #REF!
Name \r: #REF!
Name \S: #REF!
Name \t: #REF!
Name \x: #REF!
Name _\wdr: #REF!
Name ______________________________KC139: #REF!
Name _____________________________KC139: #REF!
Name ____________________________KC139: #REF!
Name ___________________________KC139: #REF!
Name __________________________KC139: #REF!
Name _________________________KC139: #REF!
Name ________________________KC139: #REF!
Name ________________________pqr1: #REF!
Name ________________________pqr2: #REF!
Name _______________________KC139: #REF!
Name _______________________pqr1: #REF!
Name _______________________pqr2: #REF!
Name ______________________KC139: #REF!
Name ______________________pqr1: #REF!
Name ______________________pqr2: #REF!
Name _____________________KC139: #REF!
Name _____________________pqr1: #REF!
Name _____________________pqr2: #REF!
Name ____________________KC139: #REF!
Name ____________________pqr1: #REF!
Name ____________________pqr2: #REF!
Name ___________________KC139: #REF!
Name __________________A65539: #REF!
Name __________________can435: 43.3
Name __________________KC139: #REF!
Name __________________pqr1: #REF!
Name __________________pqr2: #REF!
Name _________________can435: 43.3
Name _________________KC139: #REF!
Name _________________pqr1: #REF!
Name _________________pqr2: #REF!
Name ________________can435: 43.3
Name ________________KC139: #REF!
Name ________________pqr1: #REF!
Name ________________pqr2: #REF!
Name ________________sdb2: #REF!
Name _______________can430: 40.73
Name _______________can435: 43.3
Name _______________KC139: #REF!
Name _______________pqr1: #REF!
Name _______________pqr2: #REF!
Name _______________sdb2: #REF!
Name ______________can430: 40.73
Name ______________can435: 43.3
Name ______________KC139: #REF!
Name ______________pqr1: #REF!

Sheet Bill Tracker
A1: Project | B1: : Sattva City | D1: Date: | E1: 21.07.2025
A2: Vendor | B2: : Pragathi Landscapers LLP
A3: WO NO | B3: : 4300006116
A4: WO Value | B4: : Rs. 1,44,70,656.36/-
A5: Nature of Work | B5: : Landscape Works
A6: RA Bill No | B6: : 05
A7: Bill Period | B7: : 07.05.2025 to 04.07.2025
A9: WORK BILL TRACKING CHART
A10: S No | B10: Particulars | C10: Date | D10: No of Days Taken | E10: Reasons for Delay if any
A12: A | B12: PROJECTS/SITE QS/CONTRACTS DEPT.
A13: 1 | B13: Document date | C13: 05.07.2025
A14: 2 | B14: Bill Received by Project In-charge | C14: 16.07.2025
A15: 3 | B15: Bill Received by Site QS | C15: 16.07.2025
A16: 4 | B16: Contractor QS/Reqd. Information/Attachment not available
A17: 5 | B17: Other delays if any
A18: 6 | B18: Amendment/Open WO request sent to Planning
A19: 7 | B19: PR Raised by planning
A20: 8 | B20: Amendment released by Contract/Purchase Dept
A21: 9 | B21: Bill approved by Site In-charge
A22: 10 | B22: Certified/SES Entry made by Site QS (1st Level) | C22: =E1 -> 21.07.2025
A24: B | B24: BILLING, HO
A25: 1 | B25: Bill Received at HO QS
A26: 2 | B26: Bill Processed to Billing A/C
A27: 3 | B27: SES 2nd level Release
A28: 4 | B28: Tax Invoice Date
A29: 5 | B29: Corrected Tax Invoice Received
A30: 6 | B30: Parking Date
A31: 7 | B31: Received duly approved
A32: 8 | B32: Posting Date
A33: 9 | B33: Handedover to Acct. Dept.
A35: C | B35: ACCOUNTS
A36: 1 | B36: Cheque Signing List
A37: 2 | B37: Cheque handedover to Vendor.
A39: SAP WO | B39: =B3 -> : 4300006116
A40: SES NO | B40: :
A41: SAP Amount | B41: :
A42: Bill Period | B42: =B7 -> : 07.05.2025 to 04.07.2025

Sheet Checklist
A2: Salarpuria Sattva Group
A3: DOC No. | C3: ='Bill Tracker'!E1 -> 21.07.2025 | D3: Page 1 of 1
A4: Service Invoice Checklist
A6: Invoice Number:
A7: ='Bill Tracker'!D1 -> Date: | B7: ='Bill Tracker'!E1 -> 21.07.2025
A8: Single Point of Contact Number
A9: Project Name | B9: : Sattva City
A10: Project Manager | B10: : Annappa S Chikkamani
A11: S. No. | B11: Document Name | C11: Available | D11: Remarks
A12: A | B12: Checklist for Invoicing
A13: 1 | B13: Point of Contact (POC) / Work Order Number | C13: a
B14: Quantity Surveyor
A15: 2 | B15: Billing Break Up (BBU) Codes - (Nature of Works) | C15: a
A16: =A15+1 -> 3 | B16: Three Way Match: BBU Quantity - Certified Quantity - Invoice Quantity | C16: a
A17: =A16+1 -> 4 | B17: Location of Invoicing | C17: NA
A18: =A17+1 -> 5 | B18: Reconciliation of Quantity Executed/ Pending Execution | C18: NA
A19: =A18+1 -> 6 | B19: Scope Change Note/ Quantity Amendment Note | C19: NA
A20: =A19+1 -> 7 | B20: BBU / Nature of Work Rates | C20: a
A21: =A20+1 -> 8 | B21: Ad-Hoc Payment | C21: x
B22: Billing & Audit
A23: 9 | B23: Tax Rates as per Jurisdiction
A24: =A23+1 -> 10 | B24: Advance Adjustment (If Applicable)
A25: =A24+1 -> 11 | B25: Retention
A26: =A25+1 -> 12 | B26: Hold Amount
A27: =A26+1 -> 13 | B27: Car Policy
A28: =A27+1 -> 14 | B28: BG's and Validity
A29: 15 | B29: Advances
A31: B | B31: Service Documents
A32: 1 | B32: Quantity Surveyor
A33: 2 | B33: Approved Work Measurement Sheets | C33: a
A34: 3 | B34: Advance Adjustment (If Applicable) | C34: NA
A35: 4 | B35: Quality Inspection Reports (Pour Cards, Cube Test Reports etc.) | C35: NA
A36: 5 | B36: QC/Safety Clearance (If Applicable) | C36: NA
A37: 6 | B37: Material Reconciliation Report (if any) | C37: NA
A38: 7 | B38: Debit Notes | C38: NA
A39: 8 | B39: Approval of Extra Items | C39: NA
A40: 9 | B40: As-Built Drawings | C40: NA
B41: Billing & Audit
A42: 1 | B42: Abstract Sheets
A43: 2 | B43: Labour Cess Challans/Receipts
A44: 3 | B44: PF/Employees State Insurance (ESI) Copies
A45: 4 | B45: Labour License
A46: 5 | B46: Minimum Wage Act Compliance Report
A47: 6 | B47: Handover Protocols (If Applicable)
A48: 7 | B48: Tax Exemption Certificate from Client (TDS, Others)
A49: 8 | B49: Works Contract Tax Remittance against Declaration
A51: C | B51: For Raw Material Supplied
B52: Quantity Surveyor
A53: 1 | B53: Invoice | C53: NA
A54: 2 | B54: Test Certificates | C54: NA
A55: 3 | B55: Pre-dispatch clearance certificate | C55: NA
A56: 4 | B56: Weighbridge Slips | C56: NA
A58: D | B58: For Price Variation Invoices
B59: Contracts
A60: 1 | B60: Schedule of Dates
A61: 2 | B61: Schedule of Indices
A62: 3 | B62: Calculation Sheet
A63: E | B63: Other Contract Specific Document Requirements
B64: Name | C64: Designation | D64: Signature
A65: Prepared by | B65: Chethan G A | C65: Engineer-QS
A66: Approved by
B68: NA: Not applicable

Sheet PRAG SUMMURY 
A2: PROJECT :SATTVA CITY
A3: CLIENT : SATTVA CITY PRIVATE LIMITED
A4: CONTRACTOR : M/S PRAGATHI LANDSCAPERS LLP
A5: WO NO: 4300006116/R1 DATED : 03-10-2024
A6: NATURE OF WORK: HARDSCAPE WORKS | D6: RA BILL-04
F7: DATE: 14-07-2025
A8: SL No. | B8: DESCRIPTION | C8: BOQ AMOUNT | D8: PREVIOUS | E8: CURRENT | F8: CUMMULATIVE | G8: REMARKS
A10: 1 | B10: HARDSCAPE WORKS | C10: 19856639 | D10: ='Abstract '!K50 -> 0 | E10: =F10-D10 -> 632733.44 | F10: ='Abstract '!M50 -> 632733.44
B12: SUB - TOTAL | C12: =SUM(C10) -> 19856639 | D12: =SUM(D10) -> 0 | E12: =SUM(E10) -> 632733.44 | F12: =SUM(F10) -> 632733.44
B13: GST @ 18% | C13: =C12*18% -> 3574195 | D13: =D12*18% -> 0 | E13: =E12*18% -> 113892.02 | F13: =F12*18% -> 113892.02
B14: GRAND TOTAL | C14: =C12+C13 -> 23430834 | D14: =D12+D13 -> 0 | E14: =E12+E13 -> 746625.46 | F14: =F12+F13 -> 746625.46

Sheet PRAG SUM
B2: PROJECT :SATTVA CITY
B3: CLIENT : SATTVA CITY PRIVATE LIMITED
B4: CONTRACTOR : M/S PRAGATHI LANDSCAPERS LLP
B5: WO NO: 4300006116/R1 DATED : 03-10-2024
B6: NATURE OF WORK: HARDSCAPE WORKS | E6: RA BILL-03
G7: DATE: 06-05-2025
B8: SL No. | C8: DESCRIPTION | D8: BOQ AMOUNT | E8: PREVIOUS | F8: CURRENT | G8: CUMMULATIVE | H8: REMARKS
B10: 1 | C10: HARDSCAPE WORKS | D10: ='Abstract '!G50 -> 589247.24 | E10: ='Abstract '!K50 -> 0 | F10: ='Abstract '!L50 -> 632733.44 | G10: ='Abstract '!M50 -> 632733.44
C12: SUB - TOTAL | D12: =SUM(D10) -> 589247.24 | E12: =SUM(E10) -> 0 | F12: =SUM(F10) -> 632733.44 | G12: =SUM(G10) -> 632733.44
C13: GST @ 18% | D13: =D12*18% -> 106064.5 | E13: =E12*18% -> 0 | F13: =F12*18% -> 113892.02 | G13: =G12*18% -> 113892.02
C14: GRAND TOTAL | D14: =D12+D13 -> 695311.74 | E14: =E12+E13 -> 0 | F14: =F12+F13 -> 746625.46 | G14: =G12+G13 -> 746625.46

Sheet PRAG SUMMURY
B2: PROJECT :SATTVA CITY
B3: CLIENT : SATTVA CITY PRIVATE LIMITED
B4: CONTRACTOR : M/S PRAGATHI LANDSCAPERS LLP
B5: WO NO: 4300006116/R1 DATED : 03-10-2024
B6: NATURE OF WORK: HARDSCAPE WORKS | E6: RA BILL-05 & FINAL
G7: DATE: 23-10-2025
B8: SL No. | C8: DESCRIPTION | D8: BOQ AMOUNT | E8: PREVIOUS | F8: CURRENT | G8: CUMMULATIVE | H8: REMARKS
B10: 1 | C10: HARDSCAPE WORKS | D10: ='[1]Abstract '!G39 -> 19856639 | E10: ='Abstract '!K39 -> 8162761.1 | F10: =G10-E10 -> 996184.75 | G10: ='Abstract '!M39 -> 9158945.8
B12: 2 | C12: NT ITEMS | D12: 589247.24 | E12: ='Abstract '!K50 -> 0 | F12: =G12-E12 -> 632733.44 | G12: ='Abstract '!M50 -> 632733.44
C14: SUB - TOTAL | D14: =SUM(D10) -> 19856639 | E14: =SUM(E10:E12) -> 8162761.1 | F14: =SUM(F10:F12) -> 1628918.2 | G14: =SUM(G10:G12) -> 9791679.3
C15: GST @ 18% | D15: =D14*18% -> 3574195 | E15: =E14*18% -> 1469297 | F15: =F14*18% -> 293205.27 | G15: =G14*18% -> 1762502.3
C16: GRAND TOTAL | D16: =D14+D15 -> 23430834 | E16: =E14+E15 -> 9632058.1 | F16: =F14+F15 -> 1922123.5 | G16: =G14+G15 -> 11554182

Sheet Abstract 
A1: Project | B1: ='Bill Tracker'!B1 -> : Sattva City
A2: Vendor | B2: ='Bill Tracker'!B2 -> : Pragathi Landscapers LLP
A3: WO NO | B3: ='Bill Tracker'!B3 -> : 4300006116
A4: WO Value | B4: ='Bill Tracker'!B4 -> : Rs. 1,44,70,656.36/-
A5: Nature of Work | B5: ='Bill Tracker'!B5 -> : Landscape Works
A6: RA Bill No | B6: ='Bill Tracker'!B6 -> : 05
A7: Bill Period | B7: ='Bill Tracker'!B7 -> : 07.05.2025 to 04.07.2025
A8: ABSTRACT
A9: Sr.No | B9: Description | C9: SAP CODE | D9: Unit | E9: BOQ Qty | F9: Rate | G9: Amount | H9: Quantity | K9: Amount | N9: Remarks
H10: Previous | I10: Present | J10: Cumulative | K10: Previous | L10: Present | M10: Cumulative
A11: 10 | B11: Marketing office front area Hardscape
A12: 10 | B12: LAND_BASE PREPARATION BASE PREPARATION WORKS Clearing and grubbing of top 150mm top soil including cutting, removing and disposing of all materials such as trees, bushes, shrubs, stumps, roots, grass, weeds, top organic soil etc. complete. | C12: 55008371 | D12: M2 | E12: 6230.157 | F12: 60 | G12: =+E12*F12 -> 373809.42 | H12: 269.48732 | I12: =+J12-H12 -> 0 | J12: ='M BOOK'!I410 -> 269.48732 | K12: =+F12*H12 -> 16169.239 | L12: =+F12*I12 -> 0 | M12: =+J12*F12 -> 16169.239 | O12: =E12-J12 -> 5960.6697
A13: 20 | B13: LAND_SUP/FlX_PIain Concrete M10 grade PCC WORKS (1:4:8) Providing and laying Plain cement concrete 1:4:8 mix of following to the depth at locations specified at all levels using river sand, graded granite aggregate of 20mm and down size including base preparation, compaction. levelling, all leads and lifts, curing and shuttering if necessary etc., complete as per drawings. (100mm thick PCC) | C13: 55007038 | D13: M3 | E13: 623.016 | F13: 4950 | G13: =+E13*F13 -> 3083929.2 | H13: 210.01479 | I13: =+J13-H13 -> 0 | J13: ='M BOOK'!I196 -> 210.01479 | K13: =+F13*H13 -> 1039573.2 | L13: =+F13*I13 -> 0 | M13: =+J13*F13 -> 1039573.2 | O13: =E13-J13 -> 413.00121
A14: 30 | B14: 55009582 LAND_SUP/FIX_GRANITE COBBLE HARDSCAPE WORKS Black flamed Granite Cobble Stone Providing & laying of Black Granite Cobble stones of 100X100mm over 50mm thick pcc bed to required shape, size and pattern .to required line, level, etc. all complete cost including of all materials at site, necessary earth compaction, all labour charges and other charges required to complete. Location - Driveway paving band (75mm thick) | C14: 65000300 | D14: M2 | E14: 225 | F14: 3230 | G14: =+E14*F14 -> 726750 | H14: 211.5 | I14: =+J14-H14 -> 0 | J14: ='M BOOK'!I355 -> 211.5 | K14: =+F14*H14 -> 683145 | L14: =+F14*I14 -> 0 | M14: =+J14*F14 -> 683145 | O14: =E14-J14 -> 13.5
A15: 40 | B15: 55009582 LAND_SUP/FIX_GRANITE COBBLE Same as above, for paving band (40mm thick)- Pedestrian walkway | C15: 65000300 | D15: M2 | E15: 0.001 | F15: 3230 | G15: =+E15*F15 -> 3.23 | I15: =+J15-H15 -> 0 | K15: =+F15*H15 -> 0 | L15: =+F15*I15 -> 0 | M15: =+J15*F15 -> 0 | O15: =E15-J15 -> 0.001
A16: 50 | B16: LAND_FIX_CONCRETE KERBS Precast Concrete Kerb Receiving and fixing of Precast Concrete kerbs of size 150mm thick of approved make, on cement concrete base of 1:3:6 mix as per dwg, cost including all materials at site, necessary earth excavation, all labour Charges and other necessary charges all as per drawings. Location- Along Driveway | C16: 53003478 | D16: M | E16: 2318.5 | F16: 475 | G16: =+E16*F16 -> 1101287.5 | H16: 1089.1808 | I16: =+J16-H16 -> 22.66 | J16: ='M BOOK'!I96 -> 1111.8408 | K16: =+F16*H16 -> 517360.88 | L16: =+F16*I16 -> 10763.5 | M16: =+J16*F16 -> 528124.38 | O16: =E16-J16 -> 1206.6592
A17: 60 | B17: LAND_FIX_FLUSH KERBS Flush Kerb Kerbs: Receiving and fixing of Concrete flush type kerbs of size 100x300x600mm of approved make with Matte Finish, on cement concrete base of 1:3:6mix as per dwg, cost including all materials at site, necessary earth excavation. all labour charges and other necessary charges all as per drawings. Location- Along Pedestrian walkway | C17: 53003479 | D17: M | E17: 1364.75 | F17: 450 | G17: =+E17*F17 -> 614137.5 | H17: 1143.7395 | I17: =+J17-H17 -> 22.66 | J17: ='M BOOK'!I130 -> 1166.3995 | K17: =+F17*H17 -> 514682.77 | L17: =+F17*I17 -> 10197 | M17: =+J17*F17 -> 524879.78 | O17: =E17-J17 -> 198.3505 | S17: 1292.24
A18: 70 | B18: Land_sup/fix_pebbles Pebbles Supply and laying of "River washed Pebbles" of 40-50 mm dia or as per drawings. The quoted rate shall include the cost of supply, transport and laying in layers, pattern, etc., complete with cement mortor Location- Laid on waterbody drain | C18: 55003457 | D18: KG | E18: 0.001 | F18: 72 | G18: =+E18*F18 -> 0.072 | I18: =+J18-H18 -> 0 | K18: =+F18*H18 -> 0 | L18: =+F18*I18 -> 0 | M18: =+J18*F18 -> 0 | O18: =E18-J18 -> 0.001
A19: 80 | B19: LAND_FIX_BALCK GRANITE Granite Flooring Receiving and laying in position of approved Polished Jet Black Granite stone flooring of size 20mm thick as per selection laid over a bed of minimum 35mm thick cemen mortar 1:4 to the approved pattern as per the detail drawings. The joints shall be pointed with the matching cement based polymer grout with polished and unpolished surfaces of the granite slabs shall be finished with sealer coats as recommended by Laticrete/ Bal Endura/ Aqua mix or approved equivalent make and complete. Pre-polished granite slabs shall have the edges machine cut to precise sizes to produce very fine joints. All the exposed edges of the flooring shall be machine polished to profiles as per the detail drawings. This also includes providing top covering over the polythene sheets for the entire flooring to protect against scratches etc. Location- Water Feature | C19: 55007750 | D19: M2 | E19: 0.001 | F19: 1065 | G19: =+E19*F19 -> 1.065 | H19: 0 | I19: =+J19-H19 -> 0 | J19: 0 | K19: =+F19*H19 -> 0 | L19: =+F19*I19 -> 0 | M19: =+J19*F19 -> 0 | O19: =E19-J19 -> 0.001
A20: 90 | B20: F/C_FIX_Granite Cladding Granite Cladding Receving and fixing in position of 40-50mm thick approved Polished Jet Black Granite stone cladding to walls, columns and other vertical faces as called for fixed over a backing of avg 25mm thick cement mortar 1:4 and Grey Cement paste CM 1:1 to pattern as per the detail drawings. The joints shall be pointed with the matching cement based polymer grout by Laticrete or approved equivalent make and complete. Rate includes necessary scaffolding, staging, curing, etc., complete as per the instructions of the Architect / Engineer in charge. The slabs shall have the edges machine cut and polished to produce very fine joints. The cladding shall be polished if required to give the final finish as desired by architects. Rate to include wastage, providing necessary V-grooves in the joints, Granite insets in different vertical and horizontal levels/ plane as per the detail drawings if required. Location- Water Feature Location- Planter | C20: 52000566 | D20: M2 | E20: 0.001 | F20: 1136 | G20: =+E20*F20 -> 1.136 | I20: =+J20-H20 -> 0 | K20: =+F20*H20 -> 0 | L20: =+F20*I20 -> 0 | M20: =+J20*F20 -> 0 | O20: =E20-J20 -> 0.001
A21: 100 | B21: F/C_FlX_Granite Cladding above line item Location- Planter | C21: 52000566 | D21: M2 | E21: 0.001 | F21: 1136 | G21: =+E21*F21 -> 1.136 | I21: =+J21-H21 -> 0 | K21: =+F21*H21 -> 0 | L21: =+F21*I21 -> 0 | M21: =+J21*F21 -> 0 | O21: =E21-J21 -> 0.001
A22: 110 | B22: LAND_GRANITE COPING Granite Coping Receiving & Laying of 40mm thick Polished Jet Black Granite, flamed finish coping with full nosing, edge polishing on both sides in CM 1:4 over minimum thickness of 25-30mm over the masonry/RCC. The rate shall include cutting required size. laying, grouting, curing. edge finishing etc complete. Location- Water Feature 300mm width | C22: 55005650 | D22: M | E22: 0.001 | F22: 1080 | G22: =+E22*F22 -> 1.08 | I22: =+J22-H22 -> 0 | K22: =+F22*H22 -> 0 | L22: =+F22*I22 -> 0 | M22: =+J22*F22 -> 0 | O22: =E22-J22 -> 0.001
A23: 120 | B23: LAND_GRANITE COPING above line item Location- Planter 450 mm width | C23: 55005650 | D23: M | E23: 0.001 | F23: 1165 | G23: =+E23*F23 -> 1.165 | I23: =+J23-H23 -> 0 | K23: =+F23*H23 -> 0 | L23: =+F23*I23 -> 0 | M23: =+J23*F23 -> 0 | O23: =E23-J23 -> 0.001
A24: 130 | B24: LAND_FIX_CONCRETE PAVERS Concrete Pavers Receving and fixing of Concrete Pavers blocks of 200 x 100 X 80mm. laid over 35mm thick cemen mortar 1:4 , joints to be cleaned, curing, cleaning, etc. to required line, level, etc. all complete cost including of all materials at site, necessary earth compaction, all labour charges and other charges required to complete. Color- Dark Grey. For Pedestrian walkway -80mm Thick Paver | C24: 53003477 | D24: M2 | E24: 962.628 | F24: 410 | G24: =+E24*F24 -> 394677.48 | H24: 771.56951 | I24: =+J24-H24 -> 1066.5002 | J24: ='M BOOK'!I268 -> 1838.0697 | K24: =+F24*H24 -> 316343.5 | L24: =+F24*I24 -> 437265.08 | M24: =+J24*F24 -> 753608.57 | O24: =E24-J24 -> -875.44169
A25: 140 | B25: Land_SUP/Lay_Brush Finish Concrete Broom Finish Concrete Providing and laying of Concrete in M25 grade screed with water cement ratio of 0.5 of average thickness of 150mm as directed during execution and shall be laid in bays of suitable sizes and to required slope in a alternate panel fashion and neatly finished with power trowelled and lines drawn as directed, Screed Concrete shall be laid in One layer with 10 mm and down size graded stone aggregates This layer shall be thoroughly tamped, spread,incIusive of Power trowelled and finished smooth with E floating coat of neat cement. No dry cement shall be allowed to be used for finishing the surface. The surface shall be kept well watered after it is dry for a period of 8 days. Cost Shall be inclusive of making sub base area clean by removing dead mortor/concrete by chipping and laying the concrete in panels o 4mx4m providing suitable grooves. The surface Shall be finished with troll finish/broom finish etc complete. The construction joint shall be cut using diamond bit wheel for a width of 3 to 4mm and a depth of 30mm within 20 to 30 hours of concreting, no delay shall be acceptable. On curing and drying of the concrete the construction joints have to be filled with sealants as per manufacturers specification. Location- Entry Ramp | C25: 55004902 | D25: M2 | E25: 0.001 | F25: 5800 | G25: =+E25*F25 -> 5.8 | I25: =+J25-H25 -> 0 | K25: =+F25*H25 -> 0 | L25: =+F25*I25 -> 0 | M25: =+J25*F25 -> 0 | O25: =E25-J25 -> 0.001
A26: 150 | B26: LAND_POW ER TROWEL Power Trowel with broom finish for above item | C26: 55009607 | D26: M2 | E26: 1051.058 | F26: 115 | G26: =+E26*F26 -> 120871.67 | H26: 2467.1711 | I26: =+J26-H26 -> 620.76992 | J26: ='M BOOK'!I389 -> 3087.941 | K26: =+F26*H26 -> 283724.67 | L26: =+F26*I26 -> 71388.541 | M26: =+J26*F26 -> 355113.21 | O26: =E26-J26 -> -2036.883
A27: 160 | B27: LAND_GROOVE CUTTING Groove cutting for above item | C27: 55007653 | D27: M | E27: 210.8 | F27: 60 | G27: =+E27*F27 -> 12648 | H27: 357.8 | I27: =+J27-H27 -> 0 | J27: ='M BOOK'!I400 -> 357.8 | K27: =+F27*H27 -> 21468 | L27: =+F27*I27 -> 0 | M27: =+J27*F27 -> 21468 | O27: =E27-J27 -> -147
A28: 20 | B28: NT ITEMS-26-14127 | O28: =E28-J28 -> 0
A29: 10 | B29: Land_Sup/Fix_Granular Sub Base Providing & laying of Granular Sub-base with Coarse Graded material (Table:- 400-2) compacted thickness of 150mm by providing, laying, spreading and compacting , spreading in uniform layers with motor grader on prepared surface, mixing by mix in place method with rotavator at OMC, and compacting with vibratory roller 8-10 tonne to achieve the desired density of 98% including protection of edges of GSB layer, cost of all materials, labour, hire charges of machinery, loading & Unloading, all lead and lift etc., complete. as per the directions of eng-in- charge of work in accordance Technical Specification | C29: 55007561 | D29: M3 | E29: 1654.823 | F29: 2050 | G29: =+E29*F29 -> 3392387.2 | H29: 939.1261 | I29: =+J29-H29 -> 3.9111185 | J29: ='M BOOK'!I69 -> 943.03722 | K29: =+F29*H29 -> 1925208.5 | L29: =+F29*I29 -> 8017.7929 | M29: =+J29*F29 -> 1933226.3 | N29: ='DC S '!G69 -> 1082.4805 | O29: =E29-J29 -> 711.78578
A30: 20 | B30: Land_SUP/FlX_Wet Mix Macadam Providing,laying 2 layers WMM (Wet mix macadem) with Stone aggregate with approved quality of 20mm down grade and quarry dust, well packed, correct to level. The surface shall be consolidated by 8 to 10 Tonne power road roller after spreading of well compacted earth or boulder soling as the sub base etc., complete. The finish consolidated thickness shall be 150mm. | C30: 55007682 | D30: M3 | E30: 945.768 | F30: 2325 | G30: =+E30*F30 -> 2198910.6 | H30: 649.55112 | I30: =+J30-H30 -> 0 | J30: ='M BOOK'!I241 -> 649.55112 | K30: =+F30*H30 -> 1510206.4 | L30: =+F30*I30 -> 0 | M30: =+J30*F30 -> 1510206.4 | N30: ='DC S '!G131 -> 1080.15 | O30: =E30-J30 -> 296.21688
A31: 30 | B31: Land__SUP/FILL_sweet earth fill Shifting and Filling of existing soil within the site for planter box and any other location manually with consolidation. | C31: 55002290 | D31: M3 | E31: 1197.126 | F31: 240 | G31: =+E31*F31 -> 287310.24 | H31: 1430.4246 | I31: =+J31-H31 -> 69.244446 | J31: ='M BOOK'!I225 -> 1499.669 | K31: =+F31*H31 -> 343301.9 | L31: =+F31*I31 -> 16618.667 | M31: =+J31*F31 -> 359920.57 | O31: =E31-J31 -> -302.54303
A32: 40 | B32: Receiving & fixing reinforcement for RCC work with high yield strength ribbed cold twisted for steel of various diameters of grade Fe-500 confirming to BIS specificationincluding cutting, bending, fabricating, & placing in position according to drawings & binding the reinforcement with the use of 18 guage MS binding wire of double fold & providing precast cement cover blocks for main reinforecements to ensure specified cover according to relevant IS code. The measurements will be in accordance with the code IS: 1200. Note: Unless noted otherwise the measurements in accordance with IS: 1200 or equivalent BS codes. However reinforcement shall be measured only in lengths of bars as actually placed in position on standard weight basis, no allowance being made in the weight for rolling margin. Authorised laps and splices only will be measured. Chairs of any shape and profile, Spacer bar of any bshape & profile, cover block, wastage & binding wire will not be measured & shall be included in the quote rates. Quoted rate shall be deemed to have considered the above stipulation. | C32: 55010117 | D32: KG | E32: 27859.056 | F32: 16 | G32: =+E32*F32 -> 445744.9 | H32: 7260.4753 | I32: =+J32-H32 -> 4336.9927 | J32: =BBS!O69 -> 11597.468 | K32: =+F32*H32 -> 116167.6 | L32: =+F32*I32 -> 69391.884 | M32: =+J32*F32 -> 185559.49 | O32: =E32-J32 -> 16261.588
A33: 50 | B33: CHAMBER WORK (900*900* Depth up to 1.5mt) Excavation, Compaction, PCC Providing and laying 6 inch block masonry in cement mortar 1:3 (1 cement : 3 coarse sand) of in true line level and plumb for walls, with necessary scaffolding, curing etc., Providing, applying of External & internal plastering in c.m. 1:3, 15-20mm thick Single Coat including necessary scaffolding, as per design, curing and hacking to the surfaces & finish including chamber cover fixing on the top etc., complete. (Note: chamber cover supply by sattva). | C33: 55008193 | D33: NOS | E33: 11 | F33: 17400 | G33: =+E33*F33 -> 191400 | H33: 11 | I33: =+J33-H33 -> 8 | J33: ='M BOOK'!I316 -> 19 | K33: =+F33*H33 -> 191400 | L33: =+F33*I33 -> 139200 | M33: =+J33*F33 -> 330600 | O33: =E33-J33 -> -8
A34: 60 | B34: CHAMBER WORK (450*450* Depth up to 0.7mt) Excavation, Compaction, PCC Providing and laying 6 inch block masonry in cement mortar 1:3 (1 cement : 3 coarse sand) of in true line level and plumb for walls, with necessary scaffolding, curing etc., Providing, applying of External & internal plastering in c.m. 1:3, 15-20mm thick Single Coat including necessary scaffolding, as per design, curing and hacking to the surfaces & finish including chamber cover fixing on the top etc., complete. (Note: chamber cover supply by sattva) | C34: 55008193 | D34: NOS | E34: 23 | F34: 5200 | G34: =+E34*F34 -> 119600 | H34: 0 | I34: =+J34-H34 -> 0 | J34: 0 | K34: =+F34*H34 -> 0 | L34: =+F34*I34 -> 0 | M34: =+J34*F34 -> 0 | O34: =E34-J34 -> 23
A35: 70 | B35: CHAMBER WORK (600*600* Depth up to 01mt) Excavation, Compaction, PCC Providing and laying 6 inch block masonry in cement mortar 1:3 (1 cement : 3 coarse sand) of in true line level and plumb for walls, with necessary scaffolding, curing etc., Providing, applying of External & internal plastering in c.m. 1:3, 15-20mm thick Single Coat including necessary scaffolding, as per design, curing and hacking to the surfaces & finish and including chamber cover fixing on the top etc., complete. (Note: chamber cover supply by sattva) | C35: 55006453 | D35: NOS | E35: 4 | F35: 8500 | G35: =+E35*F35 -> 34000 | H35: 4 | I35: =+J35-H35 -> 0 | J35: ='M BOOK'!I324 -> 4 | K35: =+F35*H35 -> 34000 | L35: =+F35*I35 -> 0 | M35: =+J35*F35 -> 34000 | O35: =E35-J35 -> 0
A36: 80 | B36: CHAMBER WORK (750*750* Depth up to 01mt) Excavation, Compaction, PCC Providing and laying 6 inch block masonry in cement mortar 1:3 (1 cement : 3 coarse sand) of in true line level and plumb for walls, with necessary scaffolding, curing etc., Providing, applying of External & internal plastering in c.m. 1:3, 15-20mm thick Single Coat including necessary scaffolding, as per design, curing and hacking to the surfaces & finish including chamber cover fixing on the top etc., complete. (Note: chamber cover supply by sattva) | C36: 55008193 | D36: NOS | E36: 4 | F36: 10000 | G36: =+E36*F36 -> 40000 | H36: 4 | I36: =+J36-H36 -> 0 | J36: ='M BOOK'!I333 -> 4 | K36: =+F36*H36 -> 40000 | L36: =+F36*I36 -> 0 | M36: =+J36*F36 -> 40000 | O36: =E36-J36 -> 0
A37: 90 | B37: CHAMBER WORK (300*300* Depth up to 0.1mt) Excavation, Compaction, PCC Providing and laying 6 inch block masonry in cement mortar 1:3 (1 cement : 3 coarse sand) of in true line level and plumb for walls, with necessary scaffolding, curing etc., Providing, applying of External & internal plastering in c.m. 1:3, 15-20mm thick Single Coat including necessary scaffolding, as per design, curing and hacking to the surfaces & finish including chamber cover fixing on the top etc., complete. (Note: chamber cover supply by sattva) | C37: 55008193 | D37: NOS | E37: 28 | F37: 5500 | G37: =+E37*F37 -> 154000 | H37: 12 | I37: =+J37-H37 -> 18 | J37: ='M BOOK'!I346 -> 30 | K37: =+F37*H37 -> 66000 | L37: =+F37*I37 -> 99000 | M37: =+J37*F37 -> 165000 | O37: =E37-J37 -> -2
A38: 100 | B38: Receiving and laying controlled Reinforced Cement Concrete of M30 grade at all levels and heights specified below using ordinary Portland cement of grade 43 from approved manufacturer, river sand, 20mm and down size coarse aggregates, necessary admixtures approved by Consultants (Conplast SP-430SRV from Fosroc or equivalent), including all leads and lifts, pumping using line pump or boom placer, vibrating/compaction, scaffolding wherever necessary, all lead and lifts, tools & Plants, pumping the concrete to all levels, curing etc. complete but excluding cost of reinforcement and formwork, centering, shuttering. Depending on the size and location, the maximum depth of concreting will be decided by Engineer in casting at a time. | C38: 55008466 | D38: M3 | E38: 1071.98 | F38: 1100 | G38: =+E38*F38 -> 1179178 | H38: 494.55402 | I38: =+J38-H38 -> 122.12936 | J38: ='M BOOK'!I308 -> 616.68338 | K38: =+F38*H38 -> 544009.43 | L38: =+F38*I38 -> 134342.29 | M38: =+J38*F38 -> 678351.72 | O38: =E38-J38 -> 455.29662
B39: Total Amount | G39: =SUM(G12:G38) -> 14470656 | K39: =SUM(K1:K38) -> 8162761.1 | L39: =SUM(L1:L38) -> 996184.75 | M39: =SUM(M1:M38) -> 9158945.8 | O39: =E39-J39 -> 0
A40: 30 | B40: NT ITEMS-25-15179 | O40: =E40-J40 -> 0
A41: 1 | B41: Waterproofing works
A42: 40 | B42: 52008807 WP_ SUP/FIX_EXPANSION BOARD Supply and fixing of 25mm thick separation board of silplex capell HD-100 Soft board with 12mm dia dowell bars and 20mm PVC pipe with closed end filled with Grease with all material , labour and lead and lift complete as per specification. | C42: 995453 | D42: M | E42: 34 | F42: 1060 | G42: =+E42*F42 -> 36040 | I42: =+J42-H42 -> 84.3 | J42: ='NT MEAS'!I72 -> 84.3 | L42: =+F42*I42 -> 89358 | M42: =+J42*F42 -> 89358
A43: 2 | B43: Flooring / Cladding
A44: 20 | B44: F/C_FIX_Granite Flooring 40MM THICK STEEL GREY FLAMED FINISH GRANITE FLOORING-Machine cut, straight edge, with paper joint and 10mm wide 8mm deep recessed pointed groove joint between different granites, as per landscape architects details. laid over the CM 1:6mix cost including of all materials at site, all labour charges and other charges required to complete. Material Supplied by Sattva. | C44: 995474 | D44: M2 | E44: 99.92 | F44: 1466 | G44: =+E44*F44 -> 146482.72 | I44: =+J44-H44 -> 99.91514 | J44: ='NT MEAS'!I29 -> 99.91514 | L44: =+F44*I44 -> 146475.59 | M44: =+J44*F44 -> 146475.59
A45: 3 | B45: Fabrication works
A46: 10 | B46: 53000664 FAB_SUP/FIX_Saucer Drain RECEVING AND LAYING OF SAUCER DRAIN 600*300*125 MM Thick of approved make, on cement concrete base of 1:3:6 mix as per dwg, cost including all materials at site, necessary earth excavation, all labour Charges and other necessary charges all as per drawings. | C46: 995442 | D46: M | E46: 307.47 | F46: 400 | G46: =+E46*F46 -> 122988 | I46: =+J46-H46 -> 307.4677 | J46: ='NT MEAS'!I20 -> 307.4677 | L46: =+F46*I46 -> 122987.08 | M46: =+J46*F46 -> 122987.08
A47: 4 | B47: Landscape
A48: 30 | B48: 55001982 Land_SUP/FIX_polyethylene Modular sheet Providing and laying 300 micron High Density Polyethylene (HDPE) sheet below concrete pavement including all materials and labour complete | D48: M2 | E48: 2627.19 | F48: 108 | G48: =+E48*F48 -> 283736.52 | I48: =+J48-H48 -> 2536.2293 | J48: ='NT MEAS'!I65 -> 2536.2293 | L48: =+F48*I48 -> 273912.76 | M48: =+J48*F48 -> 273912.76
B50: Total Amount | G50: =SUM(G42:G48) -> 589247.24 | L50: =SUM(L42:L48) -> 632733.44 | M50: =SUM(M42:M48) -> 632733.44 | O50: =E50-J50 -> 0

Sheet NT MEAS
B2: NON-TENDERED ITEMS
B4: MEASUREMENT BACK UP
B5: SL.NO | C5: DESCRIPTION | D5: UNIT | E5: NOS | F5: L | G5: B | H5: D | I5: QTY | J5: REMARKS
B7: NT-01 | C7: SAUCER DRAIN | D7: RMT
C8: RA BILL-02
B9: AREA-01 | C9: MARKETING OFFICE DROP OFF | E9: 1 | F9: =J9/1000 -> 50.0706 | I9: =PRODUCT(E9:H9) -> 50.0706 | J9: 50070.6
E10: 1 | F10: =J10/1000 -> 18.7304 | I10: =PRODUCT(E10:H10) -> 18.7304 | J10: 18730.4
C11: RA BILL-03
B12: AREA-01 | C12: MAIN DRIVEWAY AREA | E12: 1 | F12: =J12/1000 -> 120.011 | I12: =PRODUCT(E12:H12) -> 120.011 | J12: 120011
C13: RA BILL-04
B14: AREA-01 | C14: MAIN DRIVEWAY AREA | E14: 1 | F14: =J14/1000 -> 40.0109 | I14: =PRODUCT(E14:H14) -> 40.0109 | J14: 40010.9
C16: RA BILL-04
B17: AREA-01 | C17: MAIN DRIVEWAY AREA | E17: 1 | F17: =J17/1000 -> 40.0109 | I17: =PRODUCT(E17:H17) -> 40.0109 | J17: 40010.9
B18: AREA-02 | C18: ROUNDABOUT AREA | E18: 1 | F18: =J18/1000 -> 22.815 | I18: =PRODUCT(E18:H18) -> 22.815 | J18: 22815
B19: AREA-03 | C19: ROUNDABOUT AREA | E19: 1 | F19: =J19/1000 -> 15.8189 | I19: =PRODUCT(E19:H19) -> 15.8189 | J19: 15818.9
C20: TOTAL | I20: =SUM(I9:I19) -> 307.4677 | J20: RMT | L20: =312.47/0.6 -> 520.78333
B22: SL.NO | C22: DESCRIPTION | D22: UNIT | E22: NOS | F22: L | G22: B | H22: D | I22: QTY | J22: REMARKS
B24: NT-02 | C24: 40MM THICK STEEL GREY FLAMED FINISH GRANITE FLOORING | D24: SQM
C25: RA BILL-02
B26: AREA-01 | C26: MARKETING OFFICE DROP OFF | E26: 1 | F26: =J26/(1000*1000) -> 99.91514 | I26: =PRODUCT(E26:H26) -> 99.91514 | J26: 99915140
C29: TOTAL | I29: =SUM(I26:I27) -> 99.91514 | J29: SQM
B31: SL.NO | C31: DESCRIPTION | D31: UNIT | E31: NOS | F31: L | G31: B | H31: D | I31: QTY | J31: REMARKS
B33: NT-03 | C33: HDPE SHEET 600 MICRON BELOW M30 CONCRETE | D33: SQM
C34: RA BILL-02
B35: AREA-01 | C35: CAR PARKING AREA | E35: 1 | F35: =J35/(1000*1000) -> 299.76443 | I35: =PRODUCT(E35:H35) -> 299.76443 | J35: 2.9976443e+08
C36: RA BILL-03
C37: RA BILL-04
B38: AREA-01 | C38: MAIN DRIVEWAY 1 SIDE | E38: 1 | F38: 160 | G38: 4.7 | I38: =PRODUCT(E38:H38) -> 752
B39: AREA-02 | C39: ROUNDABOUT AREA | E39: 1 | F39: =J39/1000000 -> 335.14688 | I39: =PRODUCT(E39:H39) -> 335.14688 | J39: 3.3514688e+08
C40: DEDUCTION OF COBBLE AREA | E40: -1 | F40: =J40/1000000 -> 8.0101319 | I40: =PRODUCT(E40:H40) -> -8.0101319 | J40: 8010131.9
E41: -1 | F41: =J41/1000000 -> 1.205132 | I41: =PRODUCT(E41:H41) -> -1.205132 | J41: 1205132
E42: -1 | F42: =J42/1000000 -> 0.8638683 | I42: =PRODUCT(E42:H42) -> -0.8638683 | J42: 863868.3
E43: -1 | F43: =J43/1000000 -> 6.9738893 | I43: =PRODUCT(E43:H43) -> -6.9738893 | J43: 6973889.3
E44: -1 | F44: =J44/1000000 -> 0.9008448 | I44: =PRODUCT(E44:H44) -> -0.9008448 | J44: 900844.8
E45: -1 | F45: =J45/1000000 -> 4.4952174 | I45: =PRODUCT(E45:H45) -> -4.4952174 | J45: 4495217.4
E46: -1 | F46: =J46/1000000 -> 3.2799896 | I46: =PRODUCT(E46:H46) -> -3.2799896 | J46: 3279989.6
E47: -1 | F47: =J47/1000000 -> 5.8909573 | I47: =PRODUCT(E47:H47) -> -5.8909573 | J47: 5890957.3
E48: -1 | F48: =J48/1000000 -> 7.5177032 | I48: =PRODUCT(E48:H48) -> -7.5177032 | J48: 7517703.2
E49: -1 | F49: =J49/1000000 -> 4.6961416 | I49: =PRODUCT(E49:H49) -> -4.6961416 | J49: 4696141.6
E50: -1 | F50: =J50/1000000 -> 2.3182744 | I50: =PRODUCT(E50:H50) -> -2.3182744 | J50: 2318274.4
E51: -1 | F51: =J51/1000000 -> 4.489566 | I51: =PRODUCT(E51:H51) -> -4.489566 | J51: 4489566
E52: -1 | F52: =J52/1000000 -> 2.5483965 | I52: =PRODUCT(E52:H52) -> -2.5483965 | J52: 2548396.5
B53: AREA-03 | C53: ROUNDABOUT AREA | E53: 1 | F53: =J53/1000000 -> 273.11108 | I53: =PRODUCT(E53:H53) -> 273.11108 | J53: 2.7311108e+08
C54: DEDUCTION OF COBBLE AREA | E54: -1 | F54: =J54/1000000 -> 5.8686933 | I54: =PRODUCT(E54:H54) -> -5.8686933 | J54: 5868693.3
E55: -1 | F55: =J55/1000000 -> 6.7479404 | I55: =PRODUCT(E55:H55) -> -6.7479404 | J55: 6747940.4
E56: -1 | F56: =J56/1000000 -> 3.4570348 | I56: =PRODUCT(E56:H56) -> -3.4570348 | J56: 3457034.8
E57: -1 | F57: =J57/1000000 -> 2.3659961 | I57: =PRODUCT(E57:H57) -> -2.3659961 | J57: 2365996.1
E58: -1 | F58: =J58/1000000 -> 5.4873775 | I58: =PRODUCT(E58:H58) -> -5.4873775 | J58: 5487377.5
E59: -1 | F59: =J59/1000000 -> 6.6297141 | I59: =PRODUCT(E59:H59) -> -6.6297141 | J59: 6629714.1
E60: -1 | F60: =J60/1000000 -> 2.8848351 | I60: =PRODUCT(E60:H60) -> -2.8848351 | J60: 2884835.1
E61: -1 | F61: =J61/1000000 -> 3.6483575 | I61: =PRODUCT(E61:H61) -> -3.6483575 | J61: 3648357.5
E62: -1 | F62: =J62/1000000 -> 0.6774118 | I62: =PRODUCT(E62:H62) -> -0.6774118 | J62: 677411.8
B63: AREA-04 | C63: CAR PARKING AREA DRIVEWAY | E63: 1 | F63: =J63/1000000 -> 215.16436 | I63: =PRODUCT(E63:H63) -> 215.16436 | J63: 2.1516436e+08
B64: AREA-01 | C64: MAIN DRIVEWAY AREA | E64: 1 | F64: 160 | G64: 4.7 | I64: =PRODUCT(E64:H64) -> 752
C65: TOTAL | I65: =SUM(I35:I64) -> 2536.2293 | J65: SQM
B66: =[2]ABSTRACT!B13 -> NT-04 | C66: =[2]ABSTRACT!C13 -> Supply and fixing of 25mm thick separation board of silplex capell HD-100 Soft board with 12mm dia dowell bars and 20mm PVC pipe with closed end filled with Grease with all material , labour and lead and lift complete as per specification.
C67: RA BILL-04
C68: DRIVEWAY AREA | E68: 8 | F68: 4.7 | I68: =PRODUCT(E68:H68) -> 37.6
C69: PARKING AREA | E69: 2 | F69: 6 | I69: =PRODUCT(E69:H69) -> 12
E70: 1 | F70: 4.7 | I70: =PRODUCT(E70:H70) -> 4.7
C71: ROUNDABOUT AREA | E71: 1 | F71: 30 | I71: =PRODUCT(E71:H71) -> 30
C72: TOTAL | I72: =SUM(I68:I71) -> 84.3 | J72: RMT

Sheet M BOOK
B2: ='Abstract '!A1 -> Project | C2: ='Abstract '!B1 -> : Sattva City
B3: ='Abstract '!A2 -> Vendor | C3: ='Abstract '!B2 -> : Pragathi Landscapers LLP
B4: ='Abstract '!A3 -> WO NO | C4: ='Abstract '!B3 -> : 4300006116
B5: ='Abstract '!A4 -> WO Value | C5: ='Abstract '!B4 -> : Rs. 1,44,70,656.36/-
B6: ='Abstract '!A5 -> Nature of Work | C6: ='Abstract '!B5 -> : Landscape Works
B7: ='Abstract '!A6 -> RA Bill No | C7: ='Abstract '!B6 -> : 05
B8: ='Abstract '!A7 -> Bill Period | C8: ='Abstract '!B7 -> : 07.05.2025 to 04.07.2025 | H8: DATE:23-10-2025
B9: MEASUREMENT BACK UP-RA BILL-05
B10: SL.NO | C10: DESCRIPTION | D10: UNIT | E10: NOS | F10: L | G10: B | H10: D | I10: QTY | J10: REMARKS
B12: ='Abstract '!A29 -> 10 | C12: ='Abstract '!B29 -> Land_Sup/Fix_Granular Sub Base Providing & laying of Granular Sub-base with Coarse Graded material (Table:- 400-2) compacted thickness of 150mm by providing, laying, spreading and compacting , spreading in uniform layers with motor grader on prepared surface, mixing by mix in place method with rotavator at OMC, and compacting with vibratory roller 8-10 tonne to achieve the desired density of 98% including protection of edges of GSB layer, cost of all materials, labour, hire charges of machinery, loading & Unloading, all lead and lift etc., complete. as per the directions of eng-in- charge of work in accordance Technical Specification
C13: RA BILL-01
B14: AREA-01 | C14: DRIVEWAY FROM ROUND ABOUT TOWARD ENTRACE AREA | D14: CUM | E14: 1 | F14: =J14/(1000*1000) -> 1195.8288 | H14: 0.15 | I14: =PRODUCT(E14:H14) -> 179.37432 | J14: 1.1958288e+09
B15: AREA-02 | C15: PARKING AREA-PATHWAY | E15: 1 | F15: =J15/(1000*1000) -> 352.14081 | H15: 0.15 | I15: =PRODUCT(E15:H15) -> 52.821122 | J15: 3.5214081e+08
C16: PLANTING AREA DEDUCTIONS | E16: -1 | F16: =J16/(1000*1000) -> 31.539406 | H16: 0.15 | I16: =PRODUCT(E16:H16) -> -4.7309109 | J16: 31539406
B17: AREA-03 | C17: PARKING AREA | E17: 1 | F17: =J17/(1000*1000) -> 821.29796 | H17: 0.15 | I17: =PRODUCT(E17:H17) -> 123.19469 | J17: 8.2129796e+08
B18: AREA-2A | C18: PARKING AREA-KERB BASE GSB | E18: 1 | F18: =(J18/1000)-(1.5+2.33) -> 278.7148 | G18: 0.4 | H18: 0.15 | I18: =PRODUCT(E18:H18) -> 16.722888 | J18: 282544.8
C19: PARKING AREA-KERB BASE GSB | E19: 1 | F19: =J19/1000 -> 23.7206 | G19: 0.4 | H19: 0.15 | I19: =PRODUCT(E19:H19) -> 1.423236 | J19: 23720.6
B20: AREA-3A | C20: PARKING AREA-KERB BASE GSB | E20: 1 | F20: =J20/1000 -> 169.7952 | G20: 0.4 | H20: 0.15 | I20: =PRODUCT(E20:H20) -> 10.187712 | J20: 169795.2
C21: RA BILL-02
B22: AREA-01 | C22: MARKETING OFFICE DROP OFF | E22: 1 | F22: =J22/(1000*1000) -> 408.50994 | H22: 0.15 | I22: =PRODUCT(E22:H22) -> 61.276491 | J22: 4.0850994e+08
C23: MEDIAN DEDUCTION | E23: -1 | F23: =J23/(1000*1000) -> 42.792993 | H23: 0.15 | I23: =PRODUCT(E23:H23) -> -6.4189489 | J23: 42792993
B24: AREA-02 | C24: DRIVEWAY BESIDE PATHWAY | E24: 1 | F24: =J24/(1000*1000) -> 113.20324 | H24: 0.15 | I24: =PRODUCT(E24:H24) -> 16.980485 | J24: 1.1320324e+08
B25: AREA-03 | C25: PARKING AREA PEDESTRIAN WALKWAY | E25: 1 | F25: =J25/(1000*1000) -> 79.748774 | H25: 0.15 | I25: =PRODUCT(E25:H25) -> 11.962316 | J25: 79748774
B26: AREA-04 | C26: MARKETING OFFICE DROP OFF PATHWAY | E26: 1 | F26: =J26/(1000*1000) -> 124.33505 | H26: 0.15 | I26: =PRODUCT(E26:H26) -> 18.650257 | J26: 1.2433505e+08
C27: MARKETING OFFICE DROP OFF PATHWAY | E27: 1 | F27: =J27/(1000*1000) -> 35.401722 | H27: 0.15 | I27: =PRODUCT(E27:H27) -> 5.3102583 | J27: 35401722
B28: AREA-05 | C28: MARKETING OFFICE DROP OFF GRANITE AREA | E28: 1 | F28: =J28/(1000*1000) -> 99.827298 | H28: 0.15 | I28: =PRODUCT(E28:H28) -> 14.974095 | J28: 99827298
B29: AREA-06 | C29: MARKETING OFFICE WALKWAY | E29: 1 | F29: =J29/(1000*1000) -> 56.032304 | H29: 0.15 | I29: =PRODUCT(E29:H29) -> 8.4048455 | J29: 56032304
B30: AREA-07 | C30: DRIVEWAY AREA | E30: 1 | F30: =J30/(1000*1000) -> 878.69423 | H30: 0.15 | I30: =PRODUCT(E30:H30) -> 131.80413 | J30: 8.7869423e+08
B31: AREA-08 | C31: ROUND ABOUT | E31: 1 | F31: =J31/(1000*1000) -> 480.0996 | H31: 0.15 | I31: =PRODUCT(E31:H31) -> 72.014939 | J31: 4.800996e+08
C32: KERB AREA GSB
C33: 450MM KERB Below
B34: AREA-02 | C34: MARKETING OFFICE AREA ENTRANCE | E34: 1 | F34: =J34/1000 -> 51.8133 | G34: 0.4 | H34: 0.15 | I34: =PRODUCT(E34:H34) -> 3.108798 | J34: 51813.3
E35: 1 | F35: =J35/1000 -> 20.5444 | G35: 0.4 | H35: 0.15 | I35: =PRODUCT(E35:H35) -> 1.232664 | J35: 20544.4
B36: AREA-03 | C36: ROUND ABOUT AREA | E36: 1 | F36: =J36/1000-10 -> 83.3172 | G36: 0.4 | H36: 0.15 | I36: =PRODUCT(E36:H36) -> 4.999032 | J36: 93317.2
B37: AREA-04 | C37: DRIVEWAY BESIDE WALKWAY | E37: 1 | F37: =J37/1000 -> 132.9259 | G37: 0.4 | H37: 0.15 | I37: =PRODUCT(E37:H37) -> 7.975554 | J37: 132925.9 | K37: 118
B38: AREA-05 | C38: DRIVEWAY BETWEEN PLANTER | E38: 1 | F38: =J38/1000 -> 259.6208 | G38: 0.4 | H38: 0.15 | I38: =PRODUCT(E38:H38) -> 15.577248 | J38: 259620.8
B39: AREA-06 | C39: PARKING AREA KERB | E39: 1 | F39: =J39/1000 -> 20.7902 | G39: 0.4 | H39: 0.15 | I39: =PRODUCT(E39:H39) -> 1.247412 | J39: 20790.2
E40: 1 | F40: =J40/1000 -> 56.0082 | G40: 0.4 | H40: 0.15 | I40: =PRODUCT(E40:H40) -> 3.360492 | J40: 56008.2
C41: 300MM KERB
B42: AREA-01 | C42: MARKETING OFFICE AREA WALKWAY | E42: 1 | F42: =J42/1000 -> 51.6025 | G42: 0.4 | H42: 0.15 | I42: =PRODUCT(E42:H42) -> 3.09615 | J42: 51602.5
E43: 1 | F43: =J43/1000 -> 49.1748 | G43: 0.4 | H43: 0.15 | I43: =PRODUCT(E43:H43) -> 2.950488 | J43: 49174.8
B44: AREA-07 | C44: PARKING AREA KERB | E44: 1 | F44: =J44/1000 -> 44.2927 | G44: 0.4 | H44: 0.15 | I44: =PRODUCT(E44:H44) -> 2.657562 | J44: 44292.7
E45: 1 | F45: =J45/1000 -> 45.6837 | G45: 0.4 | H45: 0.15 | I45: =PRODUCT(E45:H45) -> 2.741022 | J45: 45683.7
B46: AREA-08 | C46: PARKING AREA KERB | E46: 1 | F46: =J46/1000 -> 16.7563 | G46: 0.4 | H46: 0.15 | I46: =PRODUCT(E46:H46) -> 1.005378 | J46: 16756.3
E47: 1 | F47: =J47/1000 -> 16.6063 | G47: 0.4 | H47: 0.15 | I47: =PRODUCT(E47:H47) -> 0.996378 | J47: 16606.3
B48: AREA-09 | C48: DRIVEWAY BESIDE WALKWAY | E48: 1 | F48: =J48/1000 -> 50.0412 | G48: 0.4 | H48: 0.15 | I48: =PRODUCT(E48:H48) -> 3.002472 | J48: 50041.2
E49: 1 | F49: =J49/1000 -> 50.1043 | G49: 0.4 | H49: 0.15 | I49: =PRODUCT(E49:H49) -> 3.006258 | J49: 50104.3
B50: AREA-10 | C50: MARKETING OFFICE AREA ENTRANCE | E50: 1 | F50: =J50/1000 -> 59.8166 | G50: 0.4 | H50: 0.15 | I50: =PRODUCT(E50:H50) -> 3.588996 | J50: 59816.6
E51: 1 | F51: =J51/1000 -> 52.3787 | G51: 0.4 | H51: 0.15 | I51: =PRODUCT(E51:H51) -> 3.142722 | J51: 52378.7
B52: AREA-11 | C52: MARKETING OFFICE AREA ENTRANCE | E52: 1 | F52: =J52/1000 -> 12.2146 | G52: 0.4 | H52: 0.15 | I52: =PRODUCT(E52:H52) -> 0.732876 | J52: 12214.6
E53: 1 | F53: =J53/1000 -> 12.5692 | G53: 0.4 | H53: 0.15 | I53: =PRODUCT(E53:H53) -> 0.754152 | J53: 12569.2
C54: SAUCER DRAIN
B55: AREA-01 | C55: MARKETING OFFICE DROP OFF | E55: 1 | F55: =J55/1000 -> 50.0706 | G55: 0.4 | H55: 0.15 | I55: =PRODUCT(E55:H55) -> 3.004236 | J55: 50070.6
E56: 1 | F56: =J56/1000 -> 18.7304 | G56: 0.4 | H56: 0.15 | I56: =PRODUCT(E56:H56) -> 1.123824 | J56: 18730.4
C57: RA BILL-03
B58: AREA-01 | C58: CARPARKING AREA PEDESTRIAN WALKWAY | E58: 1 | F58: =J58/1000000 -> 52.525889 | H58: 0.15 | I58: =PRODUCT(E58:H58) -> 7.8788833 | J58: 52525889
B59: AREA-02 | C59: MARKETING OFFICE NORTHSIDE WALKWAY | E59: 1 | F59: =J59/1000000 -> 97.235765 | H59: 0.15 | I59: =PRODUCT(E59:H59) -> 14.585365 | J59: 97235765
C60: Pending area dedu | E60: -1 | F60: 3 | G60: 1.2 | H60: 0.15 | I60: =PRODUCT(E60:H60) -> -0.54
B61: AREA-03 | C61: CARPARKING DRIVEWAY AREA | E61: 1 | F61: =J61/(1000*1000) -> 216.52101 | H61: 0.15 | I61: =PRODUCT(E61:H61) -> 32.478152 | J61: 216521012
C62: RABILL-04
B63: AREA-01 | C63: ROUNDABOUT AREA | E63: 1 | F63: =J63/1000000 -> 393.85068 | H63: 0.15 | I63: =PRODUCT(E63:H63) -> 59.077602 | J63: 3.9385068e+08
B64: AREA-02 | C64: NEAR MARKETING OFFICE PAVERS AREA | E64: 1 | F64: =J64/1000000 -> 55.017173 | H64: 0.1 | I64: =PRODUCT(E64:H64) -> 5.5017173 | J64: 55017174
B65: AREA-03 | C65: MAIN DRIVEWAY BESIDE PATHWAY | E65: 1 | F65: =J65/1000000 -> 43.245087 | H65: 0.15 | I65: =PRODUCT(E65:H65) -> 6.486763 | J65: 43245087
B66: AREA-04 | C66: MAIN DRIVEWAY ENTRY SIDE AREA | E66: 1 | F66: =J66/1000000 -> 202.6798 | H66: 0.15 | I66: =PRODUCT(E66:H66) -> 30.40197 | J66: 2.026798e+08
C67: RA BILL-05
C68: INSIDE MARKETING OFFICE PLANTING AREA | E68: 1 | F68: =J68/1000000 -> 26.074123 | H68: 0.15 | I68: =PRODUCT(E68:H68) -> 3.9111185 | J68: 26074123
C69: TOTAL | I69: =SUM(I14:I68) -> 943.03722 | J69: CUM
B71: ='Abstract '!A16 -> 50 | C71: ='Abstract '!B16 -> LAND_FIX_CONCRETE KERBS Precast Concrete Kerb Receiving and fixing of Precast Concrete kerbs of size 150mm thick of approved make, on cement concrete base of 1:3:6 mix as per dwg, cost including all materials at site, necessary earth excavation, all labour Charges and other necessary charges all as per drawings. Location- Along Driveway | D71: RMT
C72: RA BILL-01
B73: AREA-02 | C73: PARKING AREA | E73: 1 | F73: =J73/1000 -> 169.7952 | I73: =PRODUCT(E73:H73) -> 169.7952 | J73: 169795.2
C74: RA BILL-02
B75: AREA-02 | C75: MARKETING OFFICE AREA ENTRANCE | E75: 1 | F75: =J75/1000 -> 51.8133 | I75: =PRODUCT(E75:H75) -> 51.8133 | J75: 51813.3
E76: 1 | F76: =J76/1000 -> 20.5444 | I76: =PRODUCT(E76:H76) -> 20.5444 | J76: 20544.4
B77: AREA-03 | C77: ROUND ABOUT AREA | E77: 1 | F77: =J77/1000-10 -> 83.3172 | I77: =PRODUCT(E77:H77) -> 83.3172 | J77: 93317.2
B78: AREA-04 | C78: DRIVEWAY BESIDE WALKWAY | E78: 1 | F78: =J78/1000 -> 132.9259 | I78: =PRODUCT(E78:H78) -> 132.9259 | J78: 132925.9
B79: AREA-05 | C79: DRIVEWAY BETWEEN PLANTER | E79: 1 | F79: =J79/1000 -> 259.6208 | I79: =PRODUCT(E79:H79) -> 259.6208 | J79: 259620.8
B80: AREA-06 | C80: PARKING AREA KERB | E80: 1 | F80: =J80/1000 -> 20.7902 | I80: =PRODUCT(E80:H80) -> 20.7902 | J80: 20790.2
E81: 1 | F81: =J81/1000 -> 56.0082 | I81: =PRODUCT(E81:H81) -> 56.0082 | J81: 56008.2
C82: RA BILL-03
B83: AREA-01 | C83: DRIVEWAY NEAR ROUND ABOUT AREA | E83: 1 | F83: =J83/1000 -> 9.79 | I83: =PRODUCT(E83:H83) -> 9.79 | J83: =9.79*1000 -> 9790
B84: AREA-03 | C84: CARPARKING DRIVEWAY AREA | E84: 1 | F84: =J84/1000 -> 49.9087 | I84: =PRODUCT(E84:H84) -> 49.9087 | J84: 49908.7
C85: RA BILL-04
B86: AREA-01 | C86: DRIVEWAY BESIDE KERB | E86: 1 | F86: =J86/1000 -> 27.0119 | I86: =PRODUCT(E86:H86) -> 27.0119 | J86: 27011.9
B87: AREA-02 | C87: DRIVEWAY BETWEEN PLANTER | E87: 2 | F87: =J87/1000 -> 27.0921 | I87: =PRODUCT(E87:H87) -> 54.1842 | J87: 27092.1
B88: AREA-03 | C88: DRIVEWAY NEAR ROUND ABOUT AREA | E88: 1 | F88: =J88/1000 -> 8.2681 | I88: =PRODUCT(E88:H88) -> 8.2681 | J88: 8268.1
B89: AREA-05 | C89: ROUNDABOUT NORTHEAST SIDE | E89: 1 | F89: =J89/1000 -> 16.3623 | I89: =PRODUCT(E89:H89) -> 16.3623 | J89: 16362.3
B90: AREA-06 | C90: AROUND CYCLE PARKING AREA | E90: 1 | F90: =J90/1000 -> 28.0798 | I90: =PRODUCT(E90:H90) -> 28.0798 | J90: 28079.8
B91: AREA-09 | C91: MARKETING OFFICE FRONTSIDE CENTRE MEDIAN | E91: 1 | F91: =J91/1000 -> 42.3377 | I91: =PRODUCT(E91:H91) -> 42.3377 | J91: 42337.7
B92: AREA-11 | C92: MAIN DRIVEWAY EXIT SIDE AREA | E92: 1 | F92: =J92/1000 -> 51.0857 | I92: =PRODUCT(E92:H92) -> 51.0857 | J92: 51085.7
B93: AREA-12 | C93: CYCLE PARKING AREA ENTRY SIDE | E93: 1 | F93: =J93/1000 -> 7.3372 | I93: =PRODUCT(E93:H93) -> 7.3372 | J93: 7337.2
C94: RA BILL-05
B95: AREA-01 | C95: DRIVEWAY BESIDE KERBSTONE WORK | E95: 1 | F95: 22.66 | I95: =PRODUCT(E95:H95) -> 22.66
C96: TOTAL | I96: =SUM(I73:I95) -> 1111.8408 | J96: RMT
B98: ='Abstract '!A17 -> 60 | C98: ='Abstract '!B17 -> LAND_FIX_FLUSH KERBS Flush Kerb Kerbs: Receiving and fixing of Concrete flush type kerbs of size 100x300x600mm of approved make with Matte Finish, on cement concrete base of 1:3:6mix as per dwg, cost including all materials at site, necessary earth excavation. all labour charges and other necessary charges all as per drawings. Location- Along Pedestrian walkway | D98: RMT
C99: RA BILL-01
B100: AREA-01 | C100: PARKING AREA-PATHWAY | D100: RMT | E100: 1 | F100: =(J100/1000)-(1.5+2.33) -> 278.7148 | I100: =PRODUCT(E100:H100) -> 278.7148 | J100: 282544.8
D101: RMT | E101: 1 | F101: =J101/1000 -> 23.7496 | I101: =PRODUCT(E101:H101) -> 23.7496 | J101: 23749.6
C102: RA BILL-02
B103: AREA-01 | C103: MARKETING OFFICE AREA WALKWAY | E103: 1 | F103: =J103/1000 -> 51.6025 | I103: =PRODUCT(E103:H103) -> 51.6025 | J103: 51602.5
E104: 1 | F104: =J104/1000 -> 49.1748 | I104: =PRODUCT(E104:H104) -> 49.1748 | J104: 49174.8
...

Sheet BBS
B1: BAR BENDING SCHEDULE RA BILL-05
B2: REINFORCEMENT WORKS
B3: Sl. No | C3: TYPE | D3: Description | E3: SHAPE OF BAR | I3: Dia | J3: Spacing | K3: No of Members | L3: Nos of Bars | M3: Lap Length | N3: Cutting length(m) | O3: 8mm | P3: 10mm | Q3: 12mm | R3: 16mm | S3: 20mm | T3: 25mm | U3: 28mm | V3: 32mm | W3: TOTAL | X3: Remarks
E4: L1 | F4: L2 | G4: L3 | H4: Ld
B5: AREA-01 | D5: CAR PARKING AREA
C6: Slab | D6: VERTICAL BARS | I6: 8 | J6: 0.225 | K6: 1 | L6: =ROUND(F9/J6+1,0) -> 223 | N6: =SUM(E7:H7) -> 5.95 | O6: =N6*L6*K6 -> 1326.85 | W6: =O6 -> 1326.85
F7: =6-0.05 -> 5.95
D8: HORIZONTAL BARS | I8: 8 | J8: 0.225 | K8: 1 | L8: =ROUND(F7/J8+1,0) -> 27 | N8: =SUM(E9:H9) -> 51.5 | O8: =N8*L8*K8 -> 1390.5 | W8: =O8 -> 1390.5
F9: =(25-0.05)*2 -> 49.9 | H9: =4*50*0.008 -> 1.6
D11: RA BILL-03
B12: AREA-01 | D12: MAIN DRIVEWAY AREA
C13: Slab | D13: VERTICAL BARS | I13: 8 | J13: 0.225 | K13: 1 | L13: =ROUND(F16/J13+1,0) -> 712 | N13: =SUM(E14:H14) -> 4.65 | O13: =N13*L13*K13 -> 3310.8 | W13: =O13 -> 3310.8
F14: =4.7-0.05 -> 4.65
D15: HORIZONTAL BARS | I15: 8 | J15: 0.225 | K15: 1 | L15: =ROUND(F14/J15+1,0) -> 22 | N15: =SUM(E16:H16) -> 165.15 | O15: =N15*L15*K15 -> 3633.3 | W15: =O15 -> 3633.3
F16: =(160-0.05) -> 159.95 | H16: =13*50*0.008 -> 5.2
D18: RA BILL-04
B19: AREA-01 | D19: MAIN DRIVEWAY AREA
C20: Slab | D20: VERTICAL BARS | I20: 8 | J20: 0.225 | K20: 1 | L20: =ROUND(F23/J20+1,0) -> 712 | N20: =SUM(E21:H21) -> 4.65 | O20: =N20*L20*K20 -> 3310.8 | W20: =O20 -> 3310.8
F21: =4.7-0.05 -> 4.65
D22: HORIZONTAL BARS | I22: 8 | J22: 0.225 | K22: 1 | L22: =ROUND(F21/J22+1,0) -> 22 | N22: =SUM(E23:H23) -> 165.2 | O22: =N22*L22*K22 -> 3634.4 | W22: =O22 -> 3634.4
F23: 160 | H23: =13*50*0.008 -> 5.2
B25: AREA-02 | D25: CARPARKING DRIVEWAY AREA
C26: Slab | D26: VERTICAL BARS | I26: 8 | J26: 0.225 | K26: 1 | L26: =ROUND(F29/J26+1,0) -> 27 | N26: =SUM(E27:H27) -> 4.95 | O26: =N26*L26*K26 -> 133.65 | W26: =O26 -> 133.65
F27: =5-0.05 -> 4.95
D28: HORIZONTAL BARS | I28: 8 | J28: 0.225 | K28: 1 | L28: =ROUND(F27/J28+1,0) -> 23 | N28: =SUM(E29:H29) -> 5.95 | O28: =N28*L28*K28 -> 136.85 | W28: =O28 -> 136.85
F29: =6-0.05 -> 5.95
B31: AREA-02 | C31: Slab | D31: VERTICAL BARS | I31: 8 | J31: 0.225 | K31: 1 | L31: =ROUND(F34/J31+1,0) -> 145 | N31: =SUM(E32:H32) -> 4.65 | O31: =N31*L31*K31 -> 674.25 | W31: =O31 -> 674.25
F32: =4.7-0.05 -> 4.65
D33: HORIZONTAL BARS | I33: 8 | J33: 0.225 | K33: 1 | L33: =ROUND(F32/J33+1,0) -> 22 | N33: =SUM(E34:H34) -> 33.2 | O33: =N33*L33*K33 -> 730.4 | W33: =O33 -> 730.4
F34: =32.45-0.05 -> 32.4 | H34: =2*50*0.008 -> 0.8
B36: AREA-03 | D36: MAIN DRIVEWAY ENTRY COBBLE AREA
C37: Slab | D37: VERTICAL BARS | I37: 8 | J37: 0.15 | K37: 1 | L37: =ROUND(F40/J37+1,0) -> 11 | N37: =SUM(E38:H38) -> 4.65 | O37: =N37*L37*K37 -> 51.15 | W37: =O37 -> 51.15
F38: =4.7-0.05 -> 4.65
D39: HORIZONTAL BARS | I39: 8 | J39: 0.15 | K39: 1 | L39: =ROUND(F38/J39+1,0) -> 32 | N39: =SUM(E40:H40) -> 1.5 | O39: =N39*L39*K39 -> 48 | W39: =O39 -> 48
F40: 1.5
D42: RA BILL-05
B43: AREA-01 | D43: ROUND ABOUT AREA
D44: VERTICAL BARS | I44: 8 | J44: 0.225 | K44: 1 | L44: 629 | N44: =SUM(E45:H45) -> 6.5 | O44: =N44*L44*K44 -> 4088.5 | W44: =O44 -> 4088.5
F45: 6.5
D47: VERTICAL BARS | I47: 8 | J47: 0.225 | K47: 1 | L47: =14.6/0.225+1 -> 65.888889 | N47: =SUM(E48:H48) -> 5.69 | O47: =N47*L47*K47 -> 374.90778 | W47: =O47 -> 374.90778
F48: 5.69
D50: VERTICAL BARS | I50: 8 | J50: 0.225 | K50: 1 | L50: =12.62/0.225+1 -> 57.088889 | N50: =SUM(E51:H51) -> 3.45 | O50: =N50*L50*K50 -> 196.95667 | W50: =O50 -> 196.95667
F51: 3.45
D53: VERTICAL BARS | I53: 8 | J53: 0.225 | K53: 1 | L53: =8.91/0.225+1 -> 40.6 | N53: =SUM(E54:H54) -> 3.7 | O53: =N53*L53*K53 -> 150.22 | W53: =O53 -> 150.22
F54: 3.7
D56: VERTICAL BARS | I56: 8 | J56: 0.225 | K56: 1 | L56: =14.6/0.225+1 -> 65.888889 | N56: =SUM(E57:H57) -> 3.85 | O56: =N56*L56*K56 -> 253.67222 | W56: =O56 -> 253.67222
F57: 3.85
D59: VERTICAL BARS | I59: 8 | J59: 0.225 | K59: 1 | L59: =14.51/0.225+1 -> 65.488889 | N59: =SUM(E60:H60) -> 5.69 | O59: =N59*L59*K59 -> 372.63178 | W59: =O59 -> 372.63178
F60: 5.69
D62: HORIZONTAL BARS | I62: 8 | J62: 0.225 | K62: 1 | L62: 1 | N62: =5470.82+72.02 -> 5542.84 | O62: =N62*L62*K62 -> 5542.84 | W62: =O62 -> 5542.84 | X62: =5470/12 -> 455.83333
X63: =X62*0.4 -> 182.33333
X64: =X63*0.395 -> 72.021667
D65: TOTAL CUTTING LENGTH dia wise in mtr | O65: =SUM(O5:O63) -> 29360.678 | P65: =SUM(P5:P39) -> 0 | Q65: =SUM(Q5:Q39) -> 0 | R65: =SUM(R5:R39) -> 0 | S65: =SUM(S5:S39) -> 0 | T65: =SUM(T5:T39) -> 0 | U65: =SUM(U5:U39) -> 0 | V65: =SUM(V5:V39) -> 0 | W65: =SUM(W5:W63) -> 29360.678
D66: Unit Weight | O66: 0.395 | P66: 0.617 | Q66: 0.888 | R66: 1.58 | S66: 2.47 | T66: 3.85 | U66: 4.83 | V66: 6.31
D67: Total (in KG) | O67: =O65*O66 -> 11597.468 | P67: =P65*P66 -> 0 | Q67: =Q65*Q66 -> 0 | R67: 0 | S67: 0 | T67: 0 | U67: 0 | V67: 0 | W67: =SUM(O67:V67) -> 11597.468
D68: Total (Diawise in MT) | O68: =O67/1000 -> 11.597468 | P68: =P67/1000 -> 0 | Q68: =Q67/1000 -> 0 | R68: 0 | S68: 0 | T68: 0 | U68: 0 | V68: 0 | W68: =SUM(O68:V68) -> 11.597468
D69: Total quantity executed till date in kg | O69: =W67 -> 11597.468 | X69: KGS
D70: Total quantity executed till date in TONNES | O70: =W68 -> 11.597468 | X70: TONNES

Sheet DC S 
C3: DCS AND ISSUE DETAILS
C5: SL NO | D5: DCNOS | E5: DATE | F5: DESCRIPTION | G5: UNIT | H5: QTY | I5: REMARKS
C6: 1 | D6: 657 | E6: 45651 | F6: GSB | G6: 34980 | H6: KG
C7: 2 | D7: 658 | E7: 45651 | F7: GSB | G7: 33800 | H7: KG
C8: 3 | D8: 659 | E8: 45651 | F8: GSB | G8: 34450 | H8: KG
C9: 4 | D9: 660 | E9: 45652 | F9: GSB | G9: 34370 | H9: KG
C10: 5 | D10: 661 | E10: 45652 | F10: GSB | G10: 33950 | H10: KG
C11: 6 | D11: 665 | E11: 45664 | F11: GSB | G11: 33960 | H11: KG
C12: 7 | D12: 666 | E12: 45664 | F12: GSB | G12: 34460 | H12: KG
C13: 8 | D13: 667 | E13: 45665 | F13: GSB | G13: 33450 | H13: KG
C14: 9 | D14: 698 | E14: 45686 | F14: GSB | G14: 38220 | H14: KG
C15: 10 | D15: 685 | E15: 45684 | F15: GSB | G15: 35220 | H15: KG
C16: 11 | D16: 687 | E16: 45685 | F16: GSB | G16: 35150 | H16: KG
C17: 12 | D17: 688 | E17: 45685 | F17: GSB | G17: 34530 | H17: KG
... C32: 27 | D32: 552 | E32: 45694 | F32: GSB | G32: 35910 | H32: KG
E33: RA BILL-02
C34: 28 | D34: 563 | E34: 45701 | F34: GSB | G34: 35890 | H34: KG
C35: 29 | D35: 571 | E35: 45703 | F35: GSB | G35: 36110 | H35: KG
C36: 30 | D36: 591 | E36: 45714 | F36: GSB | G36: 36800 | H36: KG
C37: 31 | D37: 592 | E37: 45714 | F37: GSB | G37: 36800 | H37: KG
C38: 32 | D38: 593 | E38: 45715 | F38: GSB | G38: 36800 | H38: KG
C39: 33 | D39: 600 | E39: 45717 | F39: GSB | G39: 36800 | H39: KG
C40: 34 | D40: 202 | E40: 45720 | F40: GSB | G40: 36800 | H40: KG
C41: 35 | D41: 205 | E41: 45720 | F41: GSB | G41: 36300 | H41: KG
C42: 36 | D42: 206 | E42: 45720 | F42: GSB | G42: 35610 | H42: KG
C43: 37 | D43: 207 | E43: 45726 | F43: GSB | G43: 36800 | H43: KG
C44: 38 | D44: 208 | E44: 45726 | F44: GSB | G44: 36650 | H44: KG
C45: 39 | D45: 209 | E45: 45726 | F45: GSB | G45: 36250 | H45: KG
... C67: 61 | D67: 710 | E67: 45812 | F67: GSB | G67: 37100 | H67: KG
G68: =SUM(G6:G67) -> 2273209
G69: =+G68/2100 -> 1082.4805 | H69: CUM
C70: 1 | D70: 672 | E70: 45678 | F70: WET MIX | G70: 32900 | H70: KG
C71: 2 | D71: 673 | E71: 45679 | F71: WET MIX | G71: 34250 | H71: KG
C72: 3 | D72: 674 | E72: 45679 | F72: WET MIX | G72: 35630 | H72: KG
C73: 4 | D73: 675 | E73: 45679 | F73: WET MIX | G73: 36490 | H73: KG
C74: 5 | D74: 676 | E74: 45680 | F74: WET MIX | G74: 36110 | H74: KG
C75: 6 | D75: 677 | E75: 45680 | F75: WET MIX | G75: 35910 | H75: KG
C76: 7 | D76: 678 | E76: 45680 | F76: WET MIX | G76: 35900 | H76: KG
C77: 8 | D77: 679 | E77: 45680 | F77: WET MIX | G77: 36500 | H77: KG
C78: 9 | D78: 680 | E78: 45680 | F78: WET MIX | G78: 36890 | H78: KG
C79: 10 | D79: 681 | E79: 45680 | F79: WET MIX | G79: 38520 | H79: KG
C80: 11 | D80: 681 | E80: 45681 | F80: WET MIX | G80: 36190 | H80: KG
C81: 12 | D81: 684 | E81: 45682 | F81: WET MIX | G81: 36410 | H81: KG
... C129: 60 | D129: 718 | E129: 45850 | F129: WET MIX | G129: 37090 | H129: KG
G130: =SUM(G70:G129) -> 2376330
G131: =+G130/2200 -> 1080.15 | H131: CUM
C132: 1 | D132: 551 | E132: 45689 | F132: M SAND | G132: 34200 | H132: KG
C133: 2 | D133: 654 | E133: 45646 | F133: M SAND | G133: 32800 | H133: KG
C134: 3 | D134: 682 | E134: 45680 | F134: M SAND | G134: 32750 | H134: KG
C135: 4 | D135: 564 | E135: 45702 | F135: M SAND | G135: 35570 | H135: KG
C136: 5 | D136: 598 | E136: 45716 | F136: M SAND | G136: 42270 | H136: KG
C137: 6 | D137: 599 | E137: 45716 | F137: M SAND | G137: 42270 | H137: KG
C138: 7 | D138: 204 | E138: 45720 | F138: M SAND | G138: 42270 | H138: KG
C139: 8 | D139: 214 | E139: 45728 | F139: M SAND | G139: 34950 | H139: KG
C140: 9 | D140: 215 | E140: 45734 | F140: M SAND | G140: 42270 | H140: KG
C141: 10 | D141: 221 | E141: 45745 | F141: M SAND | G141: 42270 | H141: KG
C142: 11 | D142: 230 | E142: 45760 | F142: M SAND | G142: 46410 | H142: KG
C143: 12 | D143: 248 | E143: 45786 | F143: M SAND | G143: 49290 | H143: KG
... C145: 14 | D145: 714 | E145: 45842 | F145: M SAND | G145: 34620 | H145: KG
G146: =SUM(G132:G145) -> 548280
G147: =+G146/1800 -> 304.6 | H147: CUM
C149: 1 | D149: 655 | E149: 45646 | F149: 20MM JELLY | G149: 32100 | H149: KG
C150: 2 | D150: 700 | E150: 45689 | F150: 20MM JELLY | G150: 33140 | H150: KG
G151: =SUM(G149:G150) -> 65240
G152: =+G151/1600 -> 40.775 | H152: CUM
C154: 1 | D154: 699 | E154: 45687 | F154: CEMENT | G154: 50 | H154: BAGS
C155: 2 | D155: 671 | E155: 45677 | F155: CEMENT | G155: 50 | H155: BAGS
C156: 3 | D156: 558 | E156: 45696 | F156: CEMENT | G156: 100 | H156: BAGS
C157: 4 | D157: 583 | E157: 45710 | F157: CEMENT | G157: 100 | H157: BAGS
G158: =SUM(G154:G157) -> 300 | H158: BAGS
C160: 1 | D160: 656 | E160: 45646 | F160: 4" SOLID BLOCK | G160: 700 | H160: NOS
C161: 2 | D161: 670 | E161: 45677 | F161: 6" BLOCK | G161: 300 | H161: NOS
C162: 3 | D162: 669 | E162: 45676 | F162: 6" BLOCK | G162: 300 | H162: NOS
C163: 4 | D163: 561 | E163: 45699 | F163: 6" BLOCK | G163: 500 | H163: NOS
G164: =SUM(G160:G163) -> 1800 | H164: NOS

Sheet NT
B2: NON-TENDERED ITEMS
B4: MEASUREMENT BACK UP
B5: SL.NO | C5: DESCRIPTION | D5: UNIT | E5: NOS | F5: L | G5: B | H5: D | I5: QTY | J5: REMARKS
B7: NT-01 | C7: SAUCER DRAIN | D7: RMT
C8: RA BILL-02
B9: AREA-01 | C9: MARKETING OFFICE DROP OFF | E9: 1 | F9: =J9/1000 -> 50.0706 | I9: =PRODUCT(E9:H9) -> 50.0706 | J9: 50070.6
E10: 1 | F10: =J10/1000 -> 18.7304 | I10: =PRODUCT(E10:H10) -> 18.7304 | J10: 18730.4
C11: RA BILL-03
B12: AREA-01 | C12: MAIN DRIVEWAY AREA | E12: 1 | F12: =J12/1000 -> 120.011 | I12: =PRODUCT(E12:H12) -> 120.011 | J12: 120011
C13: RA BILL-04
B14: AREA-01 | C14: MAIN DRIVEWAY AREA | E14: 1 | F14: =J14/1000 -> 40.0109 | I14: =PRODUCT(E14:H14) -> 40.0109 | J14: 40010.9
C16: RA BILL-04
B17: AREA-01 | C17: MAIN DRIVEWAY AREA | E17: 1 | F17: =J17/1000 -> 40.0109 | I17: =PRODUCT(E17:H17) -> 40.0109 | J17: 40010.9
B18: AREA-02 | C18: ROUNDABOUT AREA | E18: 1 | F18: =J18/1000 -> 22.815 | I18: =PRODUCT(E18:H18) -> 22.815 | J18: 22815
B19: AREA-03 | C19: ROUNDABOUT AREA | E19: 1 | F19: =J19/1000 -> 15.8189 | I19: =PRODUCT(E19:H19) -> 15.8189 | J19: 15818.9
C20: S | I20: =SUM(I9:I19) -> 307.4677 | J20: RMT
B22: SL.NO | C22: DESCRIPTION | D22: UNIT | E22: NOS | F22: L | G22: B | H22: D | I22: QTY | J22: REMARKS
B24: NT-02 | C24: 40MM THICK STEEL GREY FLAMED FINISH GRANITE FLOORING | D24: SQM
C25: RA BILL-02
B26: AREA-01 | C26: MARKETING OFFICE DROP OFF | E26: 1 | F26: =J26/(1000*1000) -> 99.91514 | I26: =PRODUCT(E26:H26) -> 99.91514 | J26: 99915140
C27: MODULE OFFICE FRONT SIDE | E27: 1
C28: TOTAL | I28: =SUM(I26:I26) -> 99.91514 | J28: SQM
B30: SL.NO | C30: DESCRIPTION | D30: UNIT | E30: NOS | F30: L | G30: B | H30: D | I30: QTY | J30: REMARKS
B32: NT-03 | C32: LDPE SHEET 600 MICRON BELOW M30 CONCRETE | D32: SQM
C33: RA BILL-02
B34: AREA-01 | C34: CAR PARKING AREA | E34: 1 | F34: =J34/(1000*1000) -> 299.76443 | I34: =PRODUCT(E34:H34) -> 299.76443 | J34: 2.9976443e+08
C35: RA BILL-03
C36: RA BILL-04
B37: AREA-01 | C37: MAIN DRIVEWAY 1 SIDE | E37: 1 | F37: 160 | G37: 4.7 | I37: =PRODUCT(E37:H37) -> 752
B38: AREA-02 | C38: ROUNDABOUT AREA | E38: 1 | F38: =J38/1000000 -> 335.14688 | I38: =PRODUCT(E38:H38) -> 335.14688 | J38: 3.3514688e+08
C39: DEDUCTION OF COBBLE AREA | E39: -1 | F39: =J39/1000000 -> 8.0101319 | I39: =PRODUCT(E39:H39) -> -8.0101319 | J39: 8010131.9
E40: -1 | F40: =J40/1000000 -> 1.205132 | I40: =PRODUCT(E40:H40) -> -1.205132 | J40: 1205132
E41: -1 | F41: =J41/1000000 -> 0.8638683 | I41: =PRODUCT(E41:H41) -> -0.8638683 | J41: 863868.3
E42: -1 | F42: =J42/1000000 -> 6.9738893 | I42: =PRODUCT(E42:H42) -> -6.9738893 | J42: 6973889.3
E43: -1 | F43: =J43/1000000 -> 0.9008448 | I43: =PRODUCT(E43:H43) -> -0.9008448 | J43: 900844.8
E44: -1 | F44: =J44/1000000 -> 4.4952174 | I44: =PRODUCT(E44:H44) -> -4.4952174 | J44: 4495217.4
E45: -1 | F45: =J45/1000000 -> 3.2799896 | I45: =PRODUCT(E45:H45) -> -3.2799896 | J45: 3279989.6
E46: -1 | F46: =J46/1000000 -> 5.8909573 | I46: =PRODUCT(E46:H46) -> -5.8909573 | J46: 5890957.3
E47: -1 | F47: =J47/1000000 -> 7.5177032 | I47: =PRODUCT(E47:H47) -> -7.5177032 | J47: 7517703.2
E48: -1 | F48: =J48/1000000 -> 4.6961416 | I48: =PRODUCT(E48:H48) -> -4.6961416 | J48: 4696141.6
E49: -1 | F49: =J49/1000000 -> 2.3182744 | I49: =PRODUCT(E49:H49) -> -2.3182744 | J49: 2318274.4
E50: -1 | F50: =J50/1000000 -> 4.489566 | I50: =PRODUCT(E50:H50) -> -4.489566 | J50: 4489566
E51: -1 | F51: =J51/1000000 -> 2.5483965 | I51: =PRODUCT(E51:H51) -> -2.5483965 | J51: 2548396.5
B52: AREA-03 | C52: ROUNDABOUT AREA | E52: 1 | F52: =J52/1000000 -> 273.11108 | I52: =PRODUCT(E52:H52) -> 273.11108 | J52: 2.7311108e+08
C53: DEDUCTION OF COBBLE AREA | E53: -1 | F53: =J53/1000000 -> 5.8686933 | I53: =PRODUCT(E53:H53) -> -5.8686933 | J53: 5868693.3
E54: -1 | F54: =J54/1000000 -> 6.7479404 | I54: =PRODUCT(E54:H54) -> -6.7479404 | J54: 6747940.4
E55: -1 | F55: =J55/1000000 -> 3.4570348 | I55: =PRODUCT(E55:H55) -> -3.4570348 | J55: 3457034.8
E56: -1 | F56: =J56/1000000 -> 2.3659961 | I56: =PRODUCT(E56:H56) -> -2.3659961 | J56: 2365996.1
E57: -1 | F57: =J57/1000000 -> 5.4873775 | I57: =PRODUCT(E57:H57) -> -5.4873775 | J57: 5487377.5
E58: -1 | F58: =J58/1000000 -> 6.6297141 | I58: =PRODUCT(E58:H58) -> -6.6297141 | J58: 6629714.1
E59: -1 | F59: =J59/1000000 -> 2.8848351 | I59: =PRODUCT(E59:H59) -> -2.8848351 | J59: 2884835.1
E60: -1 | F60: =J60/1000000 -> 3.6483575 | I60: =PRODUCT(E60:H60) -> -3.6483575 | J60: 3648357.5
E61: -1 | F61: =J61/1000000 -> 0.6774118 | I61: =PRODUCT(E61:H61) -> -0.6774118 | J61: 677411.8
B62: AREA-04 | C62: CAR PARKING AREA DRIVEWAY | E62: 1 | F62: =J62/1000000 -> 215.16436 | I62: =PRODUCT(E62:H62) -> 215.16436 | J62: 2.1516436e+08
B63: AREA-01 | C63: MAIN DRIVEWAY AREA | E63: 1 | F63: 160 | G63: 4.7 | I63: =PRODUCT(E63:H63) -> 752
C64: TOTAL | I64: =SUM(I34:I63) -> 2536.2293 | J64: SQM
B66: NT-04 | C66: LAND_FIX_CONCRETE PAVERS Concrete Pavers Receving and fixing of Concrete Pavers blocks of 200 x 100 X 80mm. laid over 35mm thick cemen mortar 1:4 , joints to be cleaned, curing, cleaning, etc. to required line, level, etc. all complete cost including of all materials at site, necessary earth compaction, all labour charges and other charges required to complete. Color- Dark Grey. ForPARKING AREA -80mm Thick Paver | N66: =951+883.36 -> 1834.36
C67: RA BILL-02
B68: AREA-01 | C68: PARKING AREA-LIGHT GREY | E68: 1 | F68: =J68/(1000*1000) -> 429.81072 | I68: =PRODUCT(E68:H68) -> 429.81072 | J68: 429810721 | K68: =I68 -> 429.81072
C69: MEDIAN DEDUCTION | E69: -1 | F69: =J69/(1000*1000) -> 42.793454 | I69: =PRODUCT(E69:H69) -> -42.793454 | J69: 42793454 | K69: =I69 -> -42.793454
B70: AREA-02 | C70: CAR PARKING AREA-DARK GREY | E70: 1 | F70: =J70/(1000*1000) -> 274.91021 | I70: =PRODUCT(E70:H70) -> 274.91021 | J70: 2.7491021e+08 | L70: =I70 -> 274.91021
E71: 1 | F71: =J71/(1000*1000) -> 221.433 | I71: =PRODUCT(E71:H71) -> 221.433 | J71: 2.21433e+08 | L71: =I71 -> 221.433
C72: TOTAL | I72: =SUM(I68:I71) -> 883.36047 | J72: SQM

Sheet DCS
C3: DCS AND ISSUE DETAILS
C5: SL NO | D5: DCNOS | E5: DATE | F5: DESCRIPTION | G5: UNIT | H5: QTY | I5: REMARKS
C6: 1 | D6: 657 | E6: 45651 | F6: GSB | G6: 34980 | H6: KG
C7: 2 | D7: 658 | E7: 45651 | F7: GSB | G7: 33800 | H7: KG
C8: 3 | D8: 659 | E8: 45651 | F8: GSB | G8: 34450 | H8: KG
C9: 4 | D9: 660 | E9: 45652 | F9: GSB | G9: 34370 | H9: KG
C10: 5 | D10: 661 | E10: 45652 | F10: GSB | G10: 33950 | H10: KG
C11: 6 | D11: 665 | E11: 45664 | F11: GSB | G11: 33960 | H11: KG
C12: 7 | D12: 666 | E12: 45664 | F12: GSB | G12: 34460 | H12: KG
C13: 8 | D13: 667 | E13: 45665 | F13: GSB | G13: 33450 | H13: KG
C14: 9 | D14: 698 | E14: 45686 | F14: GSB | G14: 38220 | H14: KG
C15: 10 | D15: 685 | E15: 45684 | F15: GSB | G15: 35220 | H15: KG
C16: 11 | D16: 687 | E16: 45685 | F16: GSB | G16: 35150 | H16: KG
C17: 12 | D17: 688 | E17: 45685 | F17: GSB | G17: 34530 | H17: KG
... C32: 27 | D32: 552 | E32: 45694 | F32: GSB | G32: 35910 | H32: KG
E33: RA BILL-02
C34: 28 | D34: 563 | E34: 45701 | F34: GSB | G34: 35890 | H34: KG
C35: 29 | D35: 571 | E35: 45703 | F35: GSB | G35: 36110 | H35: KG
C36: 30 | D36: 591 | E36: 45714 | F36: GSB | G36: 36800 | H36: KG
C37: 31 | D37: 592 | E37: 45714 | F37: GSB | G37: 36800 | H37: KG
C38: 32 | D38: 593 | E38: 45715 | F38: GSB | G38: 36800 | H38: KG
C39: 33 | D39: 600 | E39: 45717 | F39: GSB | G39: 36800 | H39: KG
C40: 34 | D40: 202 | E40: 45720 | F40: GSB | G40: 36800 | H40: KG
C41: 35 | D41: 205 | E41: 45720 | F41: GSB | G41: 36300 | H41: KG
C42: 36 | D42: 206 | E42: 45720 | F42: GSB | G42: 35610 | H42: KG
C43: 37 | D43: 207 | E43: 45726 | F43: GSB | G43: 36800 | H43: KG
C44: 38 | D44: 208 | E44: 45726 | F44: GSB | G44: 36650 | H44: KG
C45: 39 | D45: 209 | E45: 45726 | F45: GSB | G45: 36250 | H45: KG
... C67: 61 | D67: 710 | E67: 45812 | F67: GSB | G67: 37100 | H67: KG
G68: =SUM(G6:G67) -> 2273209
G69: =+G68/2100 -> 1082.4805 | H69: CUM
C70: 1 | D70: 672 | E70: 45678 | F70: WET MIX | G70: 32900 | H70: KG
C71: 2 | D71: 673 | E71: 45679 | F71: WET MIX | G71: 34250 | H71: KG
C72: 3 | D72: 674 | E72: 45679 | F72: WET MIX | G72: 35630 | H72: KG
C73: 4 | D73: 675 | E73: 45679 | F73: WET MIX | G73: 36490 | H73: KG
C74: 5 | D74: 676 | E74: 45680 | F74: WET MIX | G74: 36110 | H74: KG
C75: 6 | D75: 677 | E75: 45680 | F75: WET MIX | G75: 35910 | H75: KG
C76: 7 | D76: 678 | E76: 45680 | F76: WET MIX | G76: 35900 | H76: KG
C77: 8 | D77: 679 | E77: 45680 | F77: WET MIX | G77: 36500 | H77: KG
C78: 9 | D78: 680 | E78: 45680 | F78: WET MIX | G78: 36890 | H78: KG
C79: 10 | D79: 681 | E79: 45680 | F79: WET MIX | G79: 38520 | H79: KG
C80: 11 | D80: 681 | E80: 45681 | F80: WET MIX | G80: 36190 | H80: KG
C81: 12 | D81: 684 | E81: 45682 | F81: WET MIX | G81: 36410 | H81: KG
... C125: 56 | D125: 712 | E125: 45814 | F125: WET MIX | G125: 38960 | H125: KG
G126: =SUM(G70:G125) -> 2229180
G127: =+G126/2200 -> 1013.2636 | H127: CUM
C128: 1 | D128: 551 | E128: 45689 | F128: M SAND | G128: 34200 | H128: KG
C129: 2 | D129: 654 | E129: 45646 | F129: M SAND | G129: 32800 | H129: KG
C130: 3 | D130: 682 | E130: 45680 | F130: M SAND | G130: 32750 | H130: KG
C131: 4 | D131: 564 | E131: 45702 | F131: M SAND | G131: 35570 | H131: KG
C132: 5 | D132: 598 | E132: 45716 | F132: M SAND | G132: 42270 | H132: KG
C133: 6 | D133: 599 | E133: 45716 | F133: M SAND | G133: 42270 | H133: KG
C134: 7 | D134: 204 | E134: 45720 | F134: M SAND | G134: 42270 | H134: KG
C135: 8 | D135: 214 | E135: 45728 | F135: M SAND | G135: 34950 | H135: KG
C136: 9 | D136: 215 | E136: 45734 | F136: M SAND | G136: 42270 | H136: KG
C137: 10 | D137: 221 | E137: 45745 | F137: M SAND | G137: 42270 | H137: KG
C138: 11 | D138: 230 | E138: 45760 | F138: M SAND | G138: 46410 | H138: KG
C139: 12 | D139: 248 | E139: 45786 | F139: M SAND | G139: 49290 | H139: KG
C140: 13 | D140: 708 | E140: 45811 | F140: M SAND | G140: 36340 | H140: KG
G141: =SUM(G128:G140) -> 513660
G142: =+G141/1800 -> 285.36667 | H142: CUM
C144: 1 | D144: 655 | E144: 45646 | F144: 20MM JELLY | G144: 32100 | H144: KG
C145: 2 | D145: 700 | E145: 45689 | F145: 20MM JELLY | G145: 33140 | H145: KG
G146: =SUM(G144:G145) -> 65240
G147: =+G146/1600 -> 40.775 | H147: CUM
C149: 1 | D149: 699 | E149: 45687 | F149: CEMENT | G149: 50 | H149: BAGS
C150: 2 | D150: 671 | E150: 45677 | F150: CEMENT | G150: 50 | H150: BAGS
C151: 3 | D151: 558 | E151: 45696 | F151: CEMENT | G151: 100 | H151: BAGS
C152: 4 | D152: 583 | E152: 45710 | F152: CEMENT | G152: 100 | H152: BAGS
G153: =SUM(G149:G152) -> 300 | H153: BAGS
C155: 1 | D155: 656 | E155: 45646 | F155: 4" SOLID BLOCK | G155: 700 | H155: NOS
C156: 2 | D156: 670 | E156: 45677 | F156: 6" BLOCK | G156: 300 | H156: NOS
C157: 3 | D157: 669 | E157: 45676 | F157: 6" BLOCK | G157: 300 | H157: NOS
C158: 4 | D158: 561 | E158: 45699 | F158: 6" BLOCK | G158: 500 | H158: NOS
G159: =SUM(G155:G158) -> 1800 | H159: NOS

Sheet ISSUE DETAILS
C3: DCS AND ISSUE DETAILS
C5: SL NO | D5: DC/ ISSUE SLIPS | E5: DATE | F5: DESCRIPTION | G5: UNIT | H5: QTY | J5: INVOICE NO | K5: REMARKS
F6: KERB STONE
C7: 1 | D7: 069 | E7: 45646 | F7: KERB STONE 600*450*100MM | G7: NOS | H7: 360 | J7: 2830 | K7: FULL BATTER
C8: 2 | D8: 069 | E8: 45646 | F8: KERB STONE 600*450*100MM | G8: NOS | H8: 252 | J8: 2829 | K8: FULL BATTER
C9: 3 | D9: 070 | E9: 45647 | F9: KERB STONE 600*450*100MM | G9: NOS | H9: 52 | J9: 2847 | K9: FULL BATTER
C10: 4 | D10: 070 | E10: 45647 | F10: KERB STONE 600*450*100MM | G10: NOS | H10: 156 | I10: =SUM(H7:H10) -> 820 | J10: 2845 | K10: FULL BATTER
C13: 1 | D13: 004 | E13: 45681 | F13: KERB STONE 600*300*100 MM | G13: NOS | H13: 334 | J13: 3277 | K13: FLUSH
C14: 2 | D14: 078 | E14: 45649 | F14: KERB STONE 600*300*100 MM | G14: NOS | H14: 335 | J14: 2947 | K14: FLUSH
C15: 3 | D15: 021 | E15: 45334 | F15: KERB STONE 600*300*100 MM | G15: NOS | H15: 608 | J15: 3532 | K15: FLUSH
C16: 4 | D16: 021 | E16: 45334 | F16: KERB STONE 600*300*100 MM | G16: NOS | H16: 528 | J16: 3531 | K16: FLUSH | P16: =20466-P17 -> 114
C17: 5 | D17: 028 | E17: 45705 | F17: KERB STONE 600*300*100 MM | G17: NOS | H17: 576 | J17: 3599 | K17: FLUSH | L17: 576 | P17: =28240-7500-1600-50-50+600-200-10-40-300-1650+1400-1500-200-170-50-379-500-400-100+9000-320-1000-50-199-180-100-300-15-100-1350-80-100+2500-200-170-100-80-100-30-40-80+40-50-1500-40+40-35-30-50-20-400-50-1500+1500 -> 20352
C18: 6 | D18: 028 | E18: 45705 | F18: KERB STONE 600*300*100 MM | G18: NOS | H18: 512 | J18: 3597 | K18: FLUSH | P18: =+P17-15000 -> 5352
C19: 10 | D19: 051 | E19: 45719 | F19: KERB STONE 600*300*100 MM | G19: NOS | H19: 480 | J19: 3772 | K19: FLUSH
C20: 10 | D20: 052 | E20: 45719 | F20: KERB STONE 600*300*100 MM | G20: NOS | H20: 287 | J20: 3773 | K20: FLUSH
I21: =SUM(H13:H20) -> 3660
C23: 1 | D23: 100 | E23: 45677 | F23: KERB STONE 600*450*150 MM | G23: NOS | H23: 348 | J23: 3230 | K23: FULL BATTER
C24: 2 | D24: 100 | E24: 45677 | F24: KERB STONE 600*450*150 MM | G24: NOS | H24: 354 | J24: 3231 | K24: FULL BATTER
C25: 3 | D25: 034 | E25: 45707 | F25: KERB STONE 600*450*150 MM | G25: NOS | H25: 48 | J25: 3614 | K25: FULL BATTER
C26: 4 | D26: 035 | E26: 45706 | F26: KERB STONE 600*450*150 MM | G26: NOS | H26: 300 | J26: 3613
C27: 5 | D27: 028 | E27: 45705 | F27: KERB STONE 600*450*150 MM | G27: NOS | H27: 216 | J27: 3598
C28: 6 | D28: 041 | E28: 45709 | F28: KERB STONE 600*450*150 MM | G28: NOS | H28: 67 | J28: 3648
C29: 8 | D29: 035 | E29: 45706 | F29: KERB STONE 600*300*100 MM | G29: NOS | H29: 216 | J29: 3611 | K29: FLUSH
C30: 9 | D30: 035 | E30: 45706 | F30: KERB STONE 600*300*100 MM | G30: NOS | H30: 180 | J30: 3612 | K30: FLUSH
I31: =SUM(H23:H30) -> 1729
F34: SAUCER DRAIN
C35: 1 | D35: 100 | E35: 45677 | F35: SAUCER DRAIN 600*300*125 MM | G35: NOS | H35: 420 | J35: 3229
C36: 2 | D36: 100 | E36: 45677 | F36: SAUCER DRAIN 600*300*125 MM | G36: NOS | H36: 280 | J36: 3228
C37: 3 | D37: 078 | E37: 45654 | F37: SAUCER DRAIN 600*300*125 MM | G37: NOS | H37: 259 | J37: 2948
C38: 4 | D38: 034 | E38: 45707 | F38: SAUCER DRAIN 600*300*125 MM | G38: NOS | H38: 320 | J38: 3615
C39: 5 | D39: 034 | E39: 45707 | F39: SAUCER DRAIN 600*300*150 MM | G39: NOS | H39: 75 | J39: 3614
C40: 8 | D40: 072 | E40: 45649 | F40: SAUCER DRAIN 600*300*125 MM | G40: NOS | H40: 441 | J40: 2874
C41: 11 | D41: 064 | E41: 45729 | F41: SAUCER DRAIN 600*300*150 MM | G41: NOS | H41: 189 | J41: 3917
C42: 12 | D42: 064 | E42: 45729 | F42: SAUCER DRAIN 600*300*150 MM | G42: NOS | H42: 172 | J42: 3916
C43: 13 | D43: 051 | E43: 45719 | F43: SAUCER DRAIN 600*300*150 MM | G43: NOS | H43: 280 | J43: 3774
C44: 14 | D44: 052 | E44: 45719 | F44: SAUCER DRAIN 600*300*125 MM | G44: NOS | H44: 28 | J44: 3775
C45: 15 | D45: 054 | E45: 45719 | F45: SAUCER DRAIN 600*300*150 MM | G45: NOS | H45: 210 | J45: 3783
I46: =SUM(H35:H45) -> 2674
F48: CONCRETE PAVERS
C49: 1 | D49: 070 | E49: 45647 | F49: CONCRETE PAVERS LIGHT GREY-100*200*60MM | G49: SQFT | H49: 1419 | J49: 2847
C50: 3 | D50: 042 | E50: 45709 | F50: CONCRETE PAVERS LIGHT GREY-100*200*60MM | G50: SQFT | H50: 1677 | J50: 3649
C51: 4 | D51: 034 | E51: 45707 | F51: CONCRETE PAVERS LIGHT GREY-100*200*60MM | G51: SQFT | H51: 1806 | J51: 3623
C52: 5 | D52: 040 | E52: 45790 | F52: CONCRETE PAVERS LIGHT GREY-100*200*60MM | G52: SQFT | H52: 1817 | L52: =+K52/10.76 -> 0
C53: 8 | D53: 078 | E53: 46018 | F53: CONCRETE PAVERS LIGHT GREY-100*200*60MM | G53: SQFT | H53: 475 | J53: 2947
C54: 7 | D54: 054 | E54: 45719 | F54: CONCRETE PAVERS LIGHT GREY-100*200*60MM | G54: SQFT | H54: 2189 | I54: =SUM(H49:H54) -> 9383 | J54: 2780 | K54: =I54/10.76 -> 872.02602
C57: 1 | D57: 004 | E57: 45681 | F57: CONCRETE PAVERS DARK GREY-100*200*80MM | G57: SQFT | H57: 413.33 | J57: 3277
C58: 2 | D58: 004 | E58: 45681 | F58: CONCRETE PAVERS DARK GREY-100*200*80MM | G58: SQFT | H58: 1567.24 | J58: 3278
C59: 3 | D59: 072 | E59: 45649 | F59: CONCRETE PAVERS DARK GREY-100*200*80MM | G59: SQFT | H59: 1981 | J59: 2873
C60: 4 | D60: 042 | E60: 45709 | F60: CONCRETE PAVERS BLACK-100*200*80MM | G60: SQFT | H60: 516 | J60: 3650
C61: 6 | D61: 053 | E61: 45719 | F61: CONCRETE PAVERS BLACK-100*200*80MM | G61: SQFT | H61: 1858 | J61: 3782
C62: 7 | D62: 053 | E62: 45719 | F62: CONCRETE PAVERS BLACK-100*200*80MM | G62: SQFT | H62: 1445 | J62: 3781
C63: 9 | D63: 054 | E63: 45719 | F63: CONCRETE PAVERS BLACK-100*200*80MM | G63: SQFT | H63: 826 | I63: =SUM(H57:H63) -> 8606.57 | J63: 3784 | K63: =I63/10.76 -> 799.8671
F65: GRANITE
C66: 1 | D66: 083 | E66: 45664 | F66: GRANITE SADARAHALLI ANTIQUE-18MM THICK | G66: SQFT | H66: 287.81 | I66: =+H66/10.76 -> 26.748141
C67: 2 | D67: 083 | E67: 45664 | F67: GRANITE SADARAHALLI ANTIQUE-30MM THICK | G67: SQFT | H67: 57.81 | I67: =+H67/10.76 -> 5.3726766
C68: 3 | D68: 083 | E68: 45664 | F68: GRAITE JET BLACK POLISH 50MM THICK | G68: SQFT | H68: 503.03 | I68: =+H68/10.76 -> 46.75
C69: 4 | D69: 040 | E69: 45709 | F69: GRAITE JET BLACK POLISH 40MM THICK | G69: SQFT | H69: 521.805 | I69: =+H69/10.76 -> 48.494888
C70: 5 | D70: 066 | E70: 45644 | F70: GRAITE JET BLACK POLISH 40MM THICK | G70: SQFT | H70: 645.613 | I70: =+H70/10.76 -> 60.001208 | J70: 183
C71: 6 | D71: 066 | E71: 45709 | F71: GRAITE JET BLACK POLISH 30MM THICK | G71: SQFT | H71: 83.87 | I71: =+H71/10.76 -> 7.7946097 | J71: 183
C72: 7 | D72: 074 | E72: 45652 | F72: STEEL GREY GRANITE SLAB | G72: SQFT | H72: 66.9 | I72: =+H72/10.76 -> 6.2174721 | J72: 188
C73: 8 | D73: 074 | E73: 45652 | F73: STEEL GREY GRANITE 40 MM | G73: SQFT | H73: 646.18 | I73: =+H73/10.76 -> 60.053903 | J73: 188
F74: CONCRETE
C75: 1 | D75: 7791 | E75: 45696 | F75: RMC-M10 | G75: CUM | H75: 7 | J75: IS NO-039
C76: 2 | D76: 7801 | E76: 45697 | F76: RMC-M10 | G76: CUM | H76: 8
C77: 3 | D77: 7792 | E77: 45696 | F77: RMC-M10 | G77: CUM | H77: 8
C78: 4 | D78: 7879 | E78: 45700 | F78: RMC-M10 | G78: CUM | H78: 7
C79: 5 | D79: 7881 | E79: 45700 | F79: RMC-M10 | G79: CUM | H79: 5
C80: 6 | D80: 7877 | E80: 45700 | F80: RMC-M10 | G80: CUM | H80: 8
C81: 7 | D81: 8334 | E81: 45712 | F81: RMC-M10 | G81: CUM | H81: 6
C82: 8 | D82: 8338 | E82: 45712 | F82: RMC-M10 | G82: CUM | H82: 6
C83: 9 | D83: 8362 | E83: 45713 | F83: RMC-M10 | G83: CUM | H83: 8
C84: 10 | D84: 8430 | E84: 45715 | F84: RMC-M10 | G84: CUM | H84: 6
C85: 11 | D85: 8431 | E85: 45715 | F85: RMC-M10 | G85: CUM | H85: 7
C86: 12 | D86: 8432 | E86: 45715 | F86: RMC-M10 | G86: CUM | H86: 7
C87: 13 | D87: 8433 | E87: 45715 | F87: RMC-M10 | G87: CUM | H87: 7
... C109: 35 | D109: 1153 | E109: 45783 | F109: RMC-M10 | G109: CUM | H109: 4
C110: 28 | D110: 006 | E110: 45813 | F110: RMC-M10 | G110: CUM | H110: 3 | J110: 105
C111: 29 | D111: 004 | E111: 45804 | F111: RMC-M10 | G111: CUM | H111: 13 | J111: 73
C112: 30 | D112: 013 | E112: 45835 | F112: RMC-M10 | G112: CUM | H112: 6 | J112: 134
I113: =SUM(H75:H112) -> 201
C115: 1 | D115: 015 | E115: 45692 | F115: STEEL 8MM DIA | G115: MT | H115: 28.86 | I115: =SUM(H115) -> 28.86
C117: 1 | D117: 065 | E117: 45733 | F117: OPC 43 GRADE CEMENT | G117: BAGS | H117: 300
I118: =SUM(H117) -> 300 | J118: YECD1010794
F119: CONCRETE
C120: 1 | D120: 018 | E120: 45769 | F120: RMC-M30 | G120: CUM | H120: 98 | J120: 23
C121: 2 | D121: 078 | E121: 45742 | F121: RMC-M30 | G121: CUM | H121: 80 | J121: 664
C122: 3 | D122: 078 | G122: CUM | H122: =216-H120-H121 -> 38
C123: 4 | D123: 006 | E123: 45813 | F123: RMC-M30 | G123: CUM | H123: 117 | J123: 105
C124: 5 | D124: 004 | E124: 45804 | F124: RMC-M30 | G124: CUM | H124: 70 | J124: 73
C125: 6 | D125: 012 | E125: 45827 | F125: RMC-M30 | G125: CUM | H125: 55 | J125: 118
C126: 7 | D126: 016 | E126: 45841 | F126: RMC-M30 | G126: CUM | H126: 52 | I126: =SUM(H120:H126) -> 510 | J126: 144

Sheet RECON
B4: RECONCILATION SUMMARY -RA BILL-05 & FINAL
B5: SL. No | C5: NAME OF MATERIAL | D5: UNIT | E5: RECEIVED QTY | F5: CONSUMED QTY (As per RA Bill-04) | G5: Co-efficient | H5: WORK IN PROGRESS | I5: STOCK AT SITE | J5: Returned to Sattva | K5: GATEWAY RECIVED | L5: DIFFERENCE QTY | M5: PERCENTAGE OF WASTAGE | N5: REMARKS
B6: 1 | C6: KERB STONE
C7: KERB STONE 600*300*100 MM FLUSH | D7: NOS | E7: ='ISSUE DETAILS'!I21 -> 3660 | F7: =ROUND('[3]M BOOK'!I131*G7,0) -> 1910 | G7: 1.6393443 | J7: 270 | K7: 1350 | L7: =E7-F7-J7-K7 -> 130 | M7: =(L7)/E7 -> 0.035519126
C8: KERB STONE 600*450*150 MM F/B | D8: NOS | E8: ='ISSUE DETAILS'!I10+'ISSUE DETAILS'!I31 -> 2549 | F8: =ROUNDUP('[3]M BOOK'!I97*G8,0) -> 1817 | G8: 1.6393443 | K8: 1300 | L8: =E8-F8-J8-K8 -> -568 | M8: =(L8)/E8 -> -0.22283248
B9: 2 | C9: SAUCER DRAIN | L9: =E9-F9-I9-H9-J9 -> 0
C10: SAUCER DRAIN 600*300*125 MM | D10: NOS | E10: ='ISSUE DETAILS'!I46 -> 2674 | F10: =ROUNDUP('[3]NT MEAS'!I21*G10,0) -> 439 | G10: 1.6393443 | J10: 950 | K10: 600 | L10: =E10-F10-J10-K10 -> 685 | M10: =(L10)/E10 -> 0.25617053
L11: =E11-F11-I11-H11-J11 -> 0
B12: 3 | C12: CONCRETE PAVERS | D12: SQM | E12: =SUM(E13:E14) -> 1671.8931 | F12: =SUM(F13:F14) -> 1836.4197 | H12: 0 | L12: =E12-F12-J12-K12 -> -164.52657 | M12: =(L12)/E12 -> -0.098407349
C13: CONCRETE PAVERS LIGHT GREY-100*200*60MM | D13: SQM | E13: ='ISSUE DETAILS'!K54 -> 872.02602 | F13: ='[3]M BOOK'!L270 -> 1064.8502 | L13: =E13-F13-J13-K13 -> -192.82416 | M13: =(L13)/E13 -> -0.22112203
C14: CONCRETE PAVERS DARK GREY-100*200*80MM | D14: SQM | E14: ='ISSUE DETAILS'!K63 -> 799.8671 | F14: ='[3]M BOOK'!K270 -> 771.56951 | L14: =E14-F14-J14-K14 -> 28.297591 | M14: =(L14)/E14 -> 0.035377866
B16: 4 | C16: GRANITE | I16: =E16-F16-H16 -> 0
C17: GRANITE SADARAHALLI ANTIQUE-30MM THICK | D17: SQM | E17: 5.37068 | L17: =E17-F17-I17-H17-J17 -> 5.37068 | M17: =(L17)/E17 -> 1 | N17: NOT USED IN SITE
C18: GRAITE JET BLACK POLISH 50MM THICK | D18: SQM | E18: 46.128 | L18: =E18-F18-I18-H18-J18 -> 46.128 | M18: =(L18)/E18 -> 1 | N18: NOT USED IN SITE
C19: STEEL GREY GRANITE, FLAMED 40MM THK | D19: SQM | E19: 120.054 | F19: =[3]NT!I28 -> 99.91514 | L19: =E19-F19-I19-H19-J19 -> 20.13886 | M19: =(L19)/E19 -> 0.16774835
C20: STEEL GREY GRANITE, ANTIQUE FINISH- 30MM | D20: SQM | E20: 14.011 | L20: =E20-F20-I20-H20-J20 -> 14.011 | M20: =(L20)/E20 -> 1 | N20: NOT USED IN SITE
C21: SADARAHALLI ANTIQUE GRANITE 20MM THK | D21: SQM | E21: 26.228 | L21: =E21-F21-I21-H21-J21 -> 26.228 | M21: =(L21)/E21 -> 1 | N21: NOT USED IN SITE
C22: JET BLACK GRANITE POLISHED, 40MM THK | D22: SQM | E22: 108.5 | L22: =E22-F22-I22-H22-J22 -> 108.5 | M22: =(L22)/E22 -> 1 | N22: NOT USED IN SITE
C23: JET BLACK GRANITE POLISHED, 20MM THK | D23: SQM | E23: 42 | L23: =E23-F23-I23-H23-J23 -> 42 | M23: =(L23)/E23 -> 1 | N23: NOT USED IN SITE
B24: 5 | C24: CONCRETE | L24: =E24-F24-I24-H24-J24 -> 0
C25: RMC-M30 | D25: ='[3]ISSUE BACKUP'!G68 -> CUM | E25: 617 | F25: ='[3]Abstract '!J38 -> 602.99415 | L25: =E25-F25-I25-H25-J25 -> 14.005846 | M25: =(L25)/E25 -> 0.022699912
C26: RMC-M10 | D26: CUM | E26: 196 | F26: ='[3]M BOOK'!K197 -> 199.38895 | L26: =E26-F26-I26-H26-J26 -> -3.3889519 | M26: =(L26)/E26 -> -0.017290571
B27: 6 | C27: STEEL | L27: =E27-F27-I27-H27-J27 -> 0
C28: 8MM DIA STEEL | D28: MT | E28: 28.86 | F28: =[3]BBS!O70 -> 11.597468 | J28: 9.57 | K28: =4.2 -> 4.2 | L28: =E28-F28-J28-K28 -> 3.492532 | M28: =(L28)/E28 -> 0.12101636

Sheet RLS
C3: LEVELS DETAILS | I3: LEVELS DETAILS
C5: SL NO. | D5: RL | E5: FFL | F5: REMARKS | I5: SL NO. | J5: RL | K5: FFL | L5: REMARKS
C6: CAR PARKING PLANTATION AREA
C7: 1 | D7: 97.56 | E7: 98.055 | I7: 1 | J7: 97.3 | K7: 98.1
C8: 2 | D8: 97.509 | E8: 98.1 | I8: 2 | J8: 97.54 | K8: 98.05
C9: 3 | D9: 97.706 | E9: 98.13 | I9: 3 | J9: 97.824 | K9: 98.07
C10: 4 | D10: 97.548 | E10: 98.105 | I10: 4 | J10: 97.391 | K10: 98.14
C11: 5 | D11: 97.493 | E11: 98.04 | I11: 5 | J11: 97.764 | K11: 98.08
C12: 6 | D12: 97.558 | E12: 98.155 | I12: 6 | J12: 95.65 | K12: 98.01
C13: 7 | D13: 97.561 | E13: 98.015 | I13: 7 | J13: 98.79 | K13: 98.145
C14: 8 | D14: 97.617 | E14: 98.115 | I14: 8 | J14: 97.721 | K14: 98.105
C15: 9 | D15: 97.532 | E15: 98.15 | I15: 9 | J15: 97.745
C16: 10 | D16: 97.543 | E16: 98.085 | I16: 10 | J16: 97.234
C17: 11 | D17: 97.486 | E17: 98.075 | I17: 11 | J17: 97.65
C18: 12 | D18: 97.718 | E18: 97.89 | I18: AVL LEVELS | J18: =SUM(J7:J17)/11 -> 97.509909 | K18: =SUM(K7:K17)/8 -> 98.0875
C19: 13 | D19: 97.682 | E19: 98.085 | I19: DEPTH | K19: =K18-J18 -> 0.57759091 | L19: M
C20: 14 | D20: 97.755 | E20: 98.15
C21: 15 | D21: 97.64 | E21: 98.075
C22: 16 | D22: 97.484 | E22: 98.04
C23: 17 | D23: 97.51 | E23: 98.105
D24: =SUM(D7:D23) -> 1658.902 | E24: =SUM(E7:E23) -> 1667.37
C25: AVL LEVELS | D25: =+D24/17 -> 97.582471 | E25: =+E24/17 -> 98.080588
C26: DEPTH | E26: =E25-D25 -> 0.49811765 | F26: M
E30: RA BILL 03 | J30: RA BILL 03
D31: LEVELS DETAILS | I31: LEVELS DETAILS
D33: SL NO. | E33: RL | F33: FFL | G33: REMARKS | I33: SL NO. | J33: RL | K33: FFL | L33: REMARKS
D34: MARKETING OFFICE SOUTH SIDE | I34: CARPARKING AREA SOIL FILLING
D35: 1 | E35: 97.684 | F35: 97.975 | I35: 1 | J35: 97.637 | K35: 98.21
D36: 2 | E36: 97.722 | F36: 97.97 | I36: 2 | J36: 97.859 | K36: 98.215
D37: 3 | E37: 97.778 | F37: 97.96 | I37: 3 | J37: 97.718 | K37: 98.215
D38: 4 | F38: 97.99 | I38: 4 | J38: 97.628 | K38: 98.19
D39: 5 | F39: 97.965 | I39: 5 | J39: 97.682 | K39: 98.175
D40: 6 | F40: 97.96 | I40: 6 | J40: 97.682 | K40: 98.18
D41: 7 | F41: 97.975 | I41: 7 | K41: 98.205
D42: 8 | F42: 97.99 | I42: 8 | K42: 98.115
E43: =SUM(E35:E42) -> 293.184 | F43: =SUM(F35:F42) -> 783.785 | J43: =SUM(J35:J42) -> 586.206 | K43: =SUM(K35:K42) -> 785.505
D44: AVL LEVELS | E44: =+E43/3 -> 97.728 | F44: =+F43/8 -> 97.973125 | I44: AVL LEVELS | J44: =+J43/6 -> 97.701 | K44: =+K43/8 -> 98.188125
D45: DEPTH | F45: =F44-E44 -> 0.245125 | G45: M | I45: DEPTH | K45: =K44-J44 -> 0.487125 | L45: M
E47: RA BILL 03 | J47: RA BILL 03
D48: LEVELS DETAILS | I48: LEVELS DETAILS
D50: SL NO. | E50: RL | F50: FFL | G50: REMARKS | I50: SL NO. | J50: RL | K50: FFL | L50: REMARKS
D51: ELECTRIC SHED DEMOLITION LEVELS | I51: MARKETING OFFICE FRONT SIDE PLANTER AREA
D52: 1 | E52: 96.575 | F52: 97.675 | I52: 1 | J52: 97.6 | K52: 97.975
D53: 2 | E53: 96.34 | F53: 97.66 | J53: =SUM(J52:J52) -> 97.6 | K53: =SUM(K52:K52) -> 97.975
D54: 3 | E54: 96.775 | F54: 97.75 | I54: AVL LEVELS | J54: =+J53/1 -> 97.6 | K54: =+K53/1 -> 97.975
D55: 4 | E55: 96.8 | F55: 97.75 | I55: DEPTH | K55: =K54-J54 -> 0.375 | L55: M
D56: 5 | E56: 96.9 | F56: 97.66
D57: 6 | E57: 97.17 | F57: 97.665
D58: 7 | E58: 97.07 | F58: 97.67
D59: 8 | E59: 97.07 | F59: 97.665
E60: =SUM(E52:E59) -> 774.7 | F60: =SUM(F52:F59) -> 781.495
D61: AVL LEVELS | E61: =+E60/8 -> 96.8375 | F61: =+F60/8 -> 97.686875
D62: DEPTH | F62: =F61-E61 -> 0.849375 | G62: M
D68: RA BILL 04 | I68: RA BILL 04
D69: LEVELS DETAILS | I69: LEVELS DETAILS
D71: SL NO. | E71: RL | F71: FFL | G71: REMARKS | I71: SL NO. | J71: RL | K71: FFL | L71: REMARKS
D72: DRIVEWAY CENTRE MEDIAN PLANTER BOX | I72: ROUNDABOUT INSIDE FILLING AREA
D73: 1 | E73: 96.9 | F73: 97.3 | I73: 1 | J73: 97.51 | K73: 98.05
E74: =SUM(E73:E73) -> 96.9 | F74: =SUM(F73:F73) -> 97.3 | I74: 2 | J74: 97.66 | K74: 98.02
D75: AVL LEVELS | E75: =+E74/1 -> 96.9 | F75: =+F74/1 -> 97.3 | I75: 3 | J75: 97.48 | K75: 98.025
D76: DEPTH | F76: =F75-E75 -> 0.4 | G76: M | I76: 4 | J76: 97.54 | K76: 97.93
I77: 5 | J77: 97.56 | K77: 97.835
I78: 6 | J78: 97.55 | K78: 97.9
I79: 7 | J79: 97.93 | K79: 97.82
D80: RA BILL 04 | J80: =SUM(J73:J79) -> 683.23 | K80: =SUM(K73:K79) -> 685.58
D81: LEVELS DETAILS | I81: AVL LEVELS | J81: =J80/7 -> 97.604286 | K81: =K80/7 -> 97.94
I82: DEPTH | K82: =K81-J81 -> 0.33571429 | L82: M
D83: SL NO. | E83: RL | F83: FFL | G83: REMARKS
D84: DRIVEWAY BESIDE PLANTER BOX
D85: 1 | E85: 97.6 | F85: 97.975
E86: =SUM(E85:E85) -> 97.6 | F86: =SUM(F85:F85) -> 97.975
D87: AVL LEVELS | E87: =+E86/1 -> 97.6 | F87: =+F86/1 -> 97.975
D88: DEPTH | F88: =F87-E87 -> 0.375 | G88: M

Sheet ISSUE BACKUP
C3: DCS AND ISSUE DETAILS
C5: SL NO | D5: DC/ ISSUE SLIPS | E5: DATE | F5: DESCRIPTION | G5: UNIT | H5: QTY | J5: REMARKS
F6: KERB STONE
C7: 1 | D7: 069 | E7: 45646 | F7: KERB STONE 600*450*100MM | G7: NOS | H7: 360 | J7: 2830 | K7: FULL BATTER
C8: 2 | D8: 069 | E8: 45646 | F8: KERB STONE 600*450*100MM | G8: NOS | H8: 252 | J8: 2829 | K8: FULL BATTER
C9: 3 | D9: 070 | E9: 45647 | F9: KERB STONE 600*450*100MM | G9: NOS | H9: 52 | J9: 2847 | K9: FULL BATTER
C10: 4 | D10: 070 | E10: 45647 | F10: KERB STONE 600*450*100MM | G10: NOS | H10: 156 | J10: 2845 | K10: FULL BATTER
C11: 5 | D11: 070 | E11: 45647 | F11: KERB STONE 600*450*100MM | G11: NOS | H11: 360 | J11: 2830 | K11: FULL BATTER
C12: 5 | D12: 041 | E12: 45709 | F12: KERB STONE 600*450*100MM | G12: NOS | H12: 67 | I12: =SUM(H7:H12) -> 1247 | J12: 3648 | K12: FULL BATTER
C15: 1 | D15: 004 | E15: 45681 | F15: KERB STONE 600*300*100 MM | G15: NOS | H15: 334 | J15: 3277 | K15: FLUSH
C16: 2 | D16: 078 | E16: 45649 | F16: KERB STONE 600*300*100 MM | G16: NOS | H16: 335 | J16: 2947 | K16: FLUSH
C17: 3 | D17: 021 | E17: 45334 | F17: KERB STONE 600*300*100 MM | G17: NOS | H17: 608 | J17: 3532 | K17: FLUSH
C18: 4 | D18: 021 | E18: 45334 | F18: KERB STONE 600*300*100 MM | G18: NOS | H18: 528 | J18: 3531 | K18: FLUSH
C19: 5 | D19: 028 | E19: 45705 | F19: KERB STONE 600*300*100 MM | G19: NOS | H19: 576 | J19: 3599 | K19: FLUSH
C20: 6 | D20: 028 | E20: 45705 | F20: KERB STONE 600*300*100 MM | G20: NOS | H20: 512 | I20: =SUM(H15:H20) -> 2893 | J20: 3597 | K20: FLUSH
C22: 1 | D22: 100 | E22: 45677 | F22: KERB STONE 600*450*150 MM | G22: NOS | H22: 348 | J22: 3230 | K22: FULL BATTER
C23: 2 | D23: 100 | E23: 45677 | F23: KERB STONE 600*450*150 MM | G23: NOS | H23: 340 | J23: ` | K23: FULL BATTER
C24: 3 | D24: 034 | E24: 45707 | F24: KERB STONE 600*450*150 MM | G24: NOS | H24: 48 | K24: FULL BATTER
C25: 4 | D25: 035 | E25: 45706 | F25: KERB STONE 600*450*150 MM | G25: NOS | H25: 300
C26: 5 | D26: 41 | E26: 45709 | F26: KERB STONE 600*450*150 MM | G26: NOS | H26: 227 | I26: =SUM(H22:H26) -> 1263 | J26: 3648
F29: SAUCER DRAIN
C30: 1 | D30: 100 | E30: 45677 | F30: SAUCER DRAIN 600*300*125 MM | G30: NOS | H30: 405 | J30: 3229
C31: 2 | D31: 100 | E31: 45677 | F31: SAUCER DRAIN 600*300*125 MM | G31: NOS | H31: 275 | J31: 3228
C32: 3 | D32: 078 | E32: 45654 | F32: SAUCER DRAIN 600*300*125 MM | G32: NOS | H32: 259 | J32: 2948
C33: 4 | D33: 034 | E33: 45707 | F33: SAUCER DRAIN 600*300*125 MM | G33: NOS | H33: 320
C34: 5 | D34: 034 | E34: 45707 | F34: SAUCER DRAIN 600*300*150 MM | G34: NOS | H34: 75
C35: 6 | D35: 035 | E35: 45706 | F35: SAUCER DRAIN 600*300*150 MM | G35: NOS | H35: 216 | J35: 3611
C36: 7 | D36: 035 | E36: 45706 | F36: SAUCER DRAIN 600*300*150 MM | G36: NOS | H36: 180 | J36: 3612
C37: 8 | D37: 072 | E37: 45649 | F37: SAUCER DRAIN 600*300*125 MM | G37: NOS | H37: 441 | J37: 2874
C38: 9 | D38: 041 | E38: 45709 | F38: SAUCER DRAIN 600*300*125 MM | G38: NOS | H38: 42 | J38: 3648
C39: 10 | D39: 028 | E39: 45705 | F39: SAUCER DRAIN 600*300*150 MM | G39: NOS | H39: 216
C40: 11 | D40: 064 | E40: 45729 | F40: SAUCER DRAIN 600*300*150 MM | G40: NOS | H40: 189
C41: 12 | D41: 064 | E41: 45729 | F41: SAUCER DRAIN 600*300*150 MM | G41: NOS | H41: 172 | I41: =SUM(H30:H41) -> 2790 | J41: 3598
F43: CONCRETE PAVERS
C44: 1 | D44: 070 | E44: 45647 | F44: CONCRETE PAVERS LIGHT GREY-100*200*60MM | G44: SQFT | H44: 1419 | J44: 2847
C45: 2 | D45: 078 | E45: 45654 | F45: CONCRETE PAVERS LIGHT GREY-100*200*60MM | G45: SQFT | H45: 475 | J45: 2947
C46: 3 | D46: 042 | E46: 45709 | F46: CONCRETE PAVERS LIGHT GREY-100*200*60MM | G46: SQFT | H46: 1677 | J46: 3649
C47: 4 | D47: 034 | E47: 45707 | F47: CONCRETE PAVERS LIGHT GREY-100*200*60MM | G47: SQFT | H47: 1806 | J47: 3623
C48: 5 | D48: 040 | E48: 45790 | F48: CONCRETE PAVERS LIGHT GREY-100*200*60MM | G48: SQFT | H48: 1817
C49: 6 | D49: 040 | E49: 45790 | F49: CONCRETE PAVERS LIGHT GREY-100*200*60MM | G49: SQFT | H49: 1817
C50: 7 | F50: CONCRETE PAVERS LIGHT GREY-100*200*60MM | G50: SQFT | H50: 2188.8 | I50: =SUM(H44:H50) -> 11199.8
C53: 1 | D53: 004 | E53: 45681 | F53: CONCRETE PAVERS DARK GREY-100*200*80MM | G53: SQFT | H53: 413.33 | J53: 3277
C54: 2 | D54: 004 | E54: 45681 | F54: CONCRETE PAVERS DARK GREY-100*200*80MM | G54: SQFT | H54: 1567.24 | J54: 3278
C55: 3 | D55: 072 | E55: 45649 | F55: CONCRETE PAVERS DARK GREY-100*200*80MM | G55: SQFT | H55: 1981 | J55: 2873
C56: 4 | D56: 042 | E56: 45709 | F56: CONCRETE PAVERS BLACK-100*200*80MM | G56: SQFT | H56: 516
C57: 5 | D57: 064 | E57: 45729 | F57: CONCRETE PAVERS BLACK-100*200*80MM | G57: SQFT | H57: 850 | J57: 3650
C58: 6 | D58: 053 | E58: 45719 | F58: CONCRETE PAVERS BLACK-100*200*80MM | G58: SQFT | H58: 1858 | J58: 3782
C59: 7 | D59: 053 | E59: 45719 | F59: CONCRETE PAVERS BLACK-100*200*80MM | G59: SQFT | H59: 1445 | J59: 3781
C60: 8 | D60: 054 | E60: 45719 | F60: CONCRETE PAVERS BLACK-100*200*80MM | G60: SQFT | H60: 826 | I60: =SUM(H53:H60) -> 9456.57 | J60: 3781
F62: GRANITE
C63: 1 | D63: 083 | E63: 45664 | F63: GRANITE SADARAHALLI ANTIQUE-18MM THICK | G63: SQFT | H63: 287.81 | I63: =SUM(H63) -> 287.81
C64: 2 | D64: 083 | E64: 45664 | F64: GRANITE SADARAHALLI ANTIQUE-30MM THICK | G64: SQFT | H64: 57.81 | I64: =SUM(H64) -> 57.81
C65: 3 | D65: 083 | E65: 45664 | F65: GRAITE JET BLACK POLISH 50MM THICK | G65: SQFT | H65: 503.03 | I65: =SUM(H65) -> 503.03
F66: CONCRETE
C67: 1 | D67: 7791 | E67: 45696 | F67: RMC-M10 | G67: CUM | H67: 7 | J67: IS NO-039
C68: 2 | D68: 7801 | E68: 45697 | F68: RMC-M10 | G68: CUM | H68: 8
C69: 3 | D69: 7792 | E69: 45696 | F69: RMC-M10 | G69: CUM | H69: 8
C70: 4 | D70: 7879 | E70: 45700 | F70: RMC-M10 | G70: CUM | H70: 7
C71: 5 | D71: 7881 | E71: 45700 | F71: RMC-M10 | G71: CUM | H71: 5
C72: 6 | D72: 7877 | E72: 45700 | F72: RMC-M10 | G72: CUM | H72: 8
C73: 7 | D73: 8334 | E73: 45712 | F73: RMC-M10 | G73: CUM | H73: 6
C74: 8 | D74: 8338 | E74: 45712 | F74: RMC-M10 | G74: CUM | H74: 6
C75: 9 | D75: 8362 | E75: 45713 | F75: RMC-M10 | G75: CUM | H75: 8
C76: 10 | D76: 8430 | E76: 45715 | F76: RMC-M10 | G76: CUM | H76: 6
C77: 11 | D77: 8431 | E77: 45715 | F77: RMC-M10 | G77: CUM | H77: 7
C78: 12 | D78: 8432 | E78: 45715 | F78: RMC-M10 | G78: CUM | H78: 7
C79: 13 | D79: 8433 | E79: 45715 | F79: RMC-M10 | G79: CUM | H79: 7
... C101: 35 | D101: 1153 | E101: 45783 | F101: RMC-M10 | G101: CUM | H101: 4
C102: 28 | D102: 006 | E102: 45813 | F102: RMC-M10 | G102: CUM | H102: 3 | J102: 105
C103: 29 | D103: 004 | E103: 45804 | F103: RMC-M10 | G103: CUM | H103: 13 | J103: 73
C104: 30 | D104: 013 | E104: 45835 | F104: RMC-M10 | G104: CUM | H104: 6 | J104: 134
I105: =SUM(H67:H104) -> 201
C107: 1 | D107: 015 | E107: 45692 | F107: STEEL 8MM DIA | G107: MT | H107: 28.86 | I107: =SUM(H107) -> 28.86
C109: 1 | D109: 065 | E109: 45733 | F109: OPC 43 GRADE CEMENT | G109: BAGS | H109: 300
I110: =SUM(H109) -> 300 | J110: YECD1010794
F111: CONCRETE
C112: 1 | D112: 018 | E112: 45769 | F112: RMC-M30 | G112: CUM | H112: 98 | J112: 23
C113: 2 | D113: 078 | E113: 45742 | F113: RMC-M30 | G113: CUM | H113: 80 | J113: 664
C114: 3 | D114: 078 | G114: CUM | H114: =216-H112-H113 -> 38
C115: 4 | D115: 006 | E115: 45813 | F115: RMC-M30 | G115: CUM | H115: 117 | J115: 105
C116: 5 | D116: 004 | E116: 45804 | F116: RMC-M30 | G116: CUM | H116: 70 | J116: 73
C117: 6 | D117: 012 | E117: 45827 | F117: RMC-M30 | G117: CUM | H117: 55 | J117: 118
C118: 7 | D118: 016 | E118: 45841 | F118: RMC-M30 | G118: CUM | H118: 52 | I118: =SUM(H112:H118) -> 510 | J118: 144

Sheet Recovery details
A1: RMC Issued details - Pragathi Landscapers LLP
A2: Sl.No | B2: Description | C2: Unit | D2: Grade | E2: Qty | F2: Rate | G2: Amount Excluding Tax | H2: Remarks
A4: 1 | B4: Feb'24 | C4: Cum | D4: M10 | E4: 43 | F4: 3018 | G4: =E4*F4 -> 129774 | H4: Rate Reference : UNO Infracon PO No: 4000071141
A5: 2 | B5: March'24 | C5: Cum | D5: M10 | E5: 54 | F5: 3018 | G5: =E5*F5 -> 162972
A6: 3 | B6: 01.04.2025 to 06.05.2025 | C6: Cum | D6: M10 | E6: 82 | F6: 3018 | G6: =E6*F6 -> 247476
A7: 4 | B7: 07.05.2025 to 04.07.2025 | C7: Cum | D7: M10 | E7: ='Pragathi RMC Details'!E133-E4-E5-E6 -> 12 | F7: 3018 | G7: =E7*F7 -> 36216 | H7: NO concrete in this period
B9: Total | G9: =SUM(G4:G7) -> 576438
A12: Cement Issued details - Pragathi Landscapers LLP
A13: Sl.No | B13: Description | C13: Unit | D13: Grade | E13: Qty | F13: Rate | G13: Amount Including Tax | H13: Remarks
A15: 1 | B15: Cement | C15: MT | D15: 43 | E15: 15 | F15: 5800 | G15: =E15*F15 -> 87000
B18: Total | G18: =SUM(G15:G17) -> 87000

Sheet Hold Amount Details
A1: RMC Hold details - Pragathi Landscapers LLP
A2: Sl.No | B2: Description | C2: Unit | D2: Issue Qty | E2: Certified Qty | F2: Difference in Qty | G2: Rate | H2: Amount Excluding Tax | I2: Remarks
A4: 1 | B4: RMC M30 GARDE | C4: Cum | D4: =#REF! -> #REF! | E4: =#REF! -> #REF! | F4: =D4-E4 -> #REF! | G4: 3570 | H4: =F4*G4 -> #REF! | I4: Rate Reference : UNO Infracon PO No: 4000073577
B6: Total | H6: =SUM(H4:H5) -> #REF!
A9: Snag Point Hold details - Pragathi Landscapers LLP
A10: Sl.No | B10: Description | D10: Bill Vaule | E10: % of Amount Hold for Snag Points not Cleared | F10: Amount Excluding Tax | G10: Remarks
A12: 1 | B12: RA Bill 03 | D12: 1592229.7 | E12: 0.1 | F12: =ROUNDUP(D12*E12,0) -> 159223 | G12: 10% Hold Amt due to Snag Point not yet Clear
B14: Total | F14: =SUM(F12:F13) -> 159223

Sheet Pragathi RMC Details
A1: SATTVA SUPPLY RMC DETAILS /RASK - SATTVA CITY
A2: SATTVA SUPPLY RMC DETAILS/ PRAGATHI
A3: DATE | B3: SUPPLER | C3: DC NO | D3: UNIT | E3: M10 | F3: M25 | G3: M30 | H3: TOTAL QTY.
A4: 08.02.2025 | B4: UNO | C4: 7791 | D4: M3 | E4: 7 | H4: 7
A5: 08.02.2025 | B5: UNO | C5: 7792 | D5: M3 | E5: 8 | H5: 8
A6: 09.02.2025 | B6: UNO | C6: 7801 | D6: M3 | E6: 8 | H6: 8
A7: 12.02.2025 | B7: UNO | C7: 7877 | D7: M3 | E7: 8 | H7: 8
A8: 12.02.2025 | B8: UNO | C8: 7879 | D8: M3 | E8: 7 | H8: 7
A9: 12.02.2025 | B9: UNO | C9: 7881 | D9: M3 | E9: 5 | H9: 5
A10: MANTH OF FEB.1ST HALF | E10: =SUM(E4:E9) -> 43 | F10: 0 | G10: 0 | H10: 43
A11: 24.02.2025 | B11: UNO | C11: 8334 | D11: M3 | E11: 6 | H11: 6
A12: 24.02.2025 | B12: UNO | C12: 8338 | D12: M3 | E12: 6 | H12: 6
A13: 25.02.2025 | B13: UNO | C13: 8362 | D13: M3 | E13: 8 | H13: 8
A14: 27.02.2025 | B14: UNO | C14: 8430 | D14: M3 | E14: 6 | H14: 6
A15: 27.02.2025 | B15: UNO | C15: 8431 | D15: M3 | E15: 7 | H15: 7
A16: 27.02.2025 | B16: UNO | C16: 8432 | D16: M3 | E16: 7 | H16: 7
A17: 27.02.2025 | B17: UNO | C17: 8433 | D17: M3 | E17: 7 | H17: 7
A18: 27.02.2025 | B18: UNO | C18: 8334 | D18: M3 | E18: 7 | H18: 7
A19: MANTH OF FEB.2ST HALF | E19: =SUM(E11:E18) -> 54 | H19: 54
A20: 01.03.2025 | B20: UNO | C20: 8509 | D20: M3 | E20: 6 | H20: 6
A21: 01.03.2025 | B21: UNO | C21: 8516 | D21: M3 | E21: 5 | H21: 5
A22: 04.03.2025 | B22: UNO | C22: 8581 | D22: M3 | E22: 6 | H22: 6
A23: 13.03.2025 | B23: UNO | C23: 8821 | D23: M3 | E23: 3 | H23: 3
A24: 18.03.2025 | B24: UNO | C24: 8957 | D24: M3 | G24: 7 | H24: 7
A25: 18.03.2025 | B25: UNO | C25: 9860 | D25: M3 | G25: 7 | H25: 7
A26: 18.03.2025 | B26: UNO | C26: 8966 | D26: M3 | G26: 7 | H26: 7
A27: 18.03.2025 | B27: UNO | C27: 8970 | D27: M3 | G27: 8 | H27: 8
A28: 20.03.2025 | B28: UNO | C28: 9063 | D28: M3 | E28: 5 | H28: 5
A29: 20.03.2025 | B29: UNO | C29: 9065 | D29: M3 | E29: 3 | H29: 3 | K29: =70+117+55+52+107 -> 401
A30: 22.03.2025 | B30: UNO | C30: 9141 | D30: M3 | E30: 3 | H30: 3
A31: 25.03.2025 | B31: UNO | C31: 9247 | D31: M3 | G31: 7 | H31: 7
A32: 25.03.2025 | B32: UNO | C32: 9249 | D32: M3 | G32: 7 | H32: 7
A33: 25.03.2025 | B33: UNO | C33: 9250 | D33: M3 | G33: 7 | H33: 7
A34: 25.03.2025 | B34: UNO | C34: 9253 | D34: M3 | G34: 7 | H34: 7
A35: 25.03.2025 | B35: UNO | C35: 9255 | D35: M3 | G35: 7 | H35: 7
A36: 25.03.2025 | B36: UNO | C36: 9256 | D36: M3 | G36: 7 | H36: 7
A37: 25.03.2025 | B37: UNO | C37: 9266 | D37: M3 | G37: 8 | H37: 8
A38: 25.03.2025 | B38: UNO | C38: 9270 | D38: M3 | G38: 1 | H38: 1
A39: 08.03.2025 | B39: HELLA | C39: 157742 | D39: M3 | E39: 5 | H39: 5
A40: 08.03.2025 | B40: HELLA | C40: 157763 | D40: M3 | E40: 5 | H40: 5
A41: MANTH OF MARCH | E41: =SUM(E20:E40) -> 41 | F41: 0 | G41: =SUM(G20:G39) -> 80 | H41: 121
A42: 28.03.2025 | B42: uno | C42: 9378 | D42: m3 | E42: 3 | H42: 3
A43: 01.04.2025 | B43: uno | C43: 22 | D43: m3 | E43: 3 | H43: 3
A44: 02.04.2025 | B44: uno | C44: 88 | D44: m3 | G44: 7 | H44: 7
A45: 02.04.2025 | B45: uno | C45: 89 | D45: m3 | G45: 7 | H45: 7
A46: 02.04.2025 | B46: uno | C46: 91 | D46: m3 | G46: 5 | H46: 5
A47: 02.04.2025 | B47: uno | C47: 95 | D47: m3 | G47: 1 | H47: 1
A48: 04.04.2025 | B48: uno | C48: 146 | D48: m3 | G48: 7 | H48: 7
A49: 04.04.2025 | B49: uno | C49: 147 | D49: m3 | G49: 7 | H49: 7
A50: 04.04.2025 | B50: uno | C50: 148 | D50: m3 | G50: 7 | H50: 7
A51: 06.04.2025 | B51: uno | C51: 230 | D51: m3 | E51: 5 | H51: 5
A52: 08.04.2025 | B52: uno | C52: 306 | D52: m3 | G52: 7 | H52: 7
A53: 08.04.2025 | B53: uno | C53: 307 | D53: m3 | G53: 7 | H53: 7
A54: 08.04.2025 | B54: uno | C54: 308 | D54: m3 | G54: 6 | H54: 6
A55: 08.04.2025 | B55: uno | C55: 314 | D55: m3 | G55: 6 | H55: 6
A56: 08.04.2025 | B56: uno | C56: 316 | D56: m3 | G56: 6 | H56: 6
A57: 08.04.2025 | B57: uno | C57: 317 | D57: m3 | G57: 6 | H57: 6
A58: 08.04.2025 | B58: uno | C58: 323 | D58: m3 | G58: 6 | H58: 6
A59: 08.04.2025 | B59: uno | C59: 325 | D59: m3 | G59: 7 | H59: 7
A60: 08.04.2025 | B60: uno | C60: 326 | D60: m3 | G60: 6 | H60: 6
A61: 14.04.2025 | B61: uno | C61: 556 | D61: m3 | E61: 5 | H61: 5
A62: manth of april 1ts half | E62: =SUM(E42:E61) -> 16 | F62: 0 | G62: =SUM(G42:G61) -> 98 | H62: 114
A63: 17.04.2025 | B63: uno | C63: 235 | D63: M3 | E63: 3 | H63: 3
A64: 18.04.2025 | B64: uno | C64: 675 | D64: M3 | E64: 3 | H64: 3
A65: 22.04.2025 | B65: uno | C65: 786 | D65: M3 | E65: 3 | H65: 3
A66: 23.04.2025 | B66: uno | C66: 804 | D66: M3 | E66: 3 | H66: 3
A67: 24.04.2025 | B67: uno | C67: 825 | D67: M3 | E67: 3 | H67: 3
A68: 25.04.2025 | B68: uno | C68: 840 | D68: M3 | G68: 6 | H68: 6
A69: 25.04.2025 | B69: uno | C69: 841 | D69: M3 | G69: 6 | H69: 6
A70: 25.04.2025 | B70: uno | C70: 842 | D70: M3 | G70: 7 | H70: 7 | J70: =179-154 -> 25
A71: 25.04.2025 | B71: uno | C71: 844 | D71: M3 | G71: 7 | H71: 7 | J71: =16+6 -> 22
A72: 25.04.2025 | B72: uno | C72: 845 | D72: M3 | G72: 6 | H72: 6 | J72: TOTAL 47 CUM
A73: 25.04.2025 | B73: uno | C73: 849 | D73: M3 | G73: 6 | H73: 6
A74: manth of april 2st half | E74: =SUM(E63:E73) -> 15 | F74: 0 | G74: =SUM(G63:G73) -> 38 | H74: 53
A75: 04.05.2025 | B75: UNO | C75: 1088 | D75: M3 | E75: 3
A76: 06.05.2025 | B76: UNO | C76: 1182 | D76: M3 | E76: 3
A77: 06.05.2025 | B77: UNO | C77: 1153 | D77: M3 | E77: 4
A78: 10.05.2025 | B78: UNO | C78: 1293 | D78: M3 | G78: 7
A79: 10.05.2025 | B79: UNO | C79: 1298 | D79: M3 | G79: 7
A80: 10.05.2025 | B80: UNO | C80: 1303 | D80: M3 | G80: 7
A81: 10.05.2025 | B81: UNO | C81: 1312 | D81: M3 | G81: 7
A82: 11.05.2025 | B82: UNO | C82: 1351 | D82: M3 | G82: 7
A83: 11.05.2025 | B83: UNO | C83: 1353 | D83: M3 | G83: 7
A84: 11.05.2025 | B84: UNO | C84: 1357 | D84: M3 | G84: 7
A85: 11.05.2026 | B85: UNO | C85: 1359 | D85: M3 | G85: 7
A86: 11.05.2027 | B86: UNO | C86: 1361 | D86: M3 | G86: 7
A87: 11.05.2028 | B87: UNO | C87: 1363 | D87: M3 | G87: 7
A88: 13.05.2025 | B88: UNO | C88: 1394 | D88: M3 | E88: 3
A89: Month of may 1st half | E89: =SUM(E75:E88) -> 13 | F89: =SUM(F75:F88) -> 0 | G89: =SUM(G75:G88) -> 70 | H89: =SUM(H75:H88) -> 0
A90: 23.05.2025 | B90: UNO | C90: 1698 | D90: M3 | E90: 3 | H90: =SUM(E90:G90) -> 3
A91: 26.05.2025 | B91: UNO | C91: 1756 | D91: M3 | G91: 6 | H91: =SUM(E91:G91) -> 6
A92: 26.05.2025 | B92: UNO | C92: 1757 | D92: M3 | G92: 8 | H92: =SUM(E92:G92) -> 8
A93: 26.05.2025 | B93: UNO | C93: 1763 | D93: M3 | G93: 3 | H93: =SUM(E93:G93) -> 3
A94: 26.05.2025 | B94: UNO | C94: 1767 | D94: M3 | G94: 7 | H94: =SUM(E94:G94) -> 7
A95: 26.05.2025 | B95: UNO | C95: 1769 | D95: M3 | G95: 6 | H95: =SUM(E95:G95) -> 6
A96: 26.05.2025 | B96: UNO | C96: 1771 | D96: M3 | G96: 7 | H96: =SUM(E96:G96) -> 7
A97: 26.05.2025 | B97: UNO | C97: 1780 | D97: M3 | G97: 6 | H97: =SUM(E97:G97) -> 6
A98: 26.05.2025 | B98: UNO | C98: 1781 | D98: M3 | G98: 7 | H98: =SUM(E98:G98) -> 7
A99: 26.05.2025 | B99: UNO | C99: 1782 | D99: M3 | G99: 7 | H99: =SUM(E99:G99) -> 7
A100: 30.05.2025 | B100: UNO | C100: 1944 | D100: M3 | G100: 7 | H100: =SUM(E100:G100) -> 7
...
